Workbook

Sheet README
A1: SCRUTINISE — CORPUS REGISTER v4
A2: Rebuilt 23 August 2026. Supersedes Legislation_Corpus_Breakdown_v3.xlsx.
A4: WHAT THIS WORKBOOK IS
A5: Every source the Scrutinise corpus holds, should hold, or has decided not to hold — in one list, with an honest completeness figure beside each one.
A7: THE ONE THING TO UNDERSTAND FIRST
A8: The daily ingest email has been reporting 62 of 77 collections as '100% complete'. For 46 of them the target was set by copying the number of sections we ended up with, and then marking it confirmed. The email was dividing a number by itself. 100% of nothing is still 100%.
A9: The tell was on the face of the email: explanatory-notes held 18,651 sections against a target of 410 — 4,549% of target — and still printed '100% complete'.
A11: SO: WHAT DO WE ACTUALLY KNOW?
A12: Only legislation has ever been compared against the publisher's own list of what they published. That comparison — a 'walk' — is the only thing that produces a real percentage.
A13: MEASURED 7 sources. A publisher walk exists. The percentage is a fact.
A14: CLAIMED 5 sources. A target exists but nobody can say where it came from.
A15: UNMEASURED 59 sources. No denominator. NO PERCENTAGE IS SHOWN. That blank is the honest answer.
... A53: 5. Quality, not volume: 131,654 tribunal rows are landing pages; 28,629 sections from three retired collections are still being served.

Sheet Master Register
A1: ID | B1: Tier | C1: Source | D1: Corpus key | E1: Status | F1: New? | G1: Publisher | H1: Unit (what the publisher counts) | I1: Units published | J1: Units held | K1: % complete (units) | L1: Sections held | M1: Words held (V30 snapshot) | N1: Coverage state | O1: Licence code | P1: Licence status | Q1: Commercial use OK? | R1: Priority | S1: Known issue — what is wrong | T1: Work to close it | U1: Why this matters
A2: L01 | B2: T1 The law itself | C2: UK Public General Acts 2000 to date | D2: primary-acts-2000plus | E2: HELD | G2: legislation.gov.uk (TNA) | H2: Act | I2: 938 | J2: 933 | K2: =IFERROR(J2/I2,"") -> 0.99466951 | L2: 147788 | M2: 22001014 | N2: MEASURED | O2: ogl-3.0 | P2: CLEAR | Q2: Yes | R2: 1 | S2: 5 Acts published but not held. | T2: Fetch the 5 from the v36 worklist. | U2: The current statute book. Non-negotiable core.
A3: L02 | B3: T1 The law itself | C3: UK Public General Acts 1801–1999 | D3: primary-acts-pre-2000 | E3: HELD | G3: legislation.gov.uk (TNA) | H3: Act | I3: 9343 | J3: 3560 | K3: =IFERROR(J3/I3,"") -> 0.38103393 | L3: 166290 | M3: 24783975 | N3: MEASURED | O3: ogl-3.0 | P3: CLEAR | Q3: Yes | R3: 1 | S3: 5,783 Acts with text at source are not held. A further 7,279 published Acts carry no provisions and are correctly excluded. ~11.4% of held legislation sections are one-word dot-leaders (the source's rendering of a repealed provision). | T3: Fetch the 5,783 from scripts/ingest/v36/worklist.jsonl. Flag dot-leaders, do not delete. | U3: Historic statute is what makes 'is this still law?' answerable. The weakest part of the corpus.
A4: L03 | B4: T1 The law itself | C4: UK Statutory Instruments to 2009 | D4: si-pre-2010 | E4: HELD | G4: legislation.gov.uk (TNA) | H4: SI | I4: see L04 | J4: see L04 | L4: 462809 | M4: 61581830 | N4: MEASURED | O4: ogl-3.0 | P4: CLEAR | Q4: Yes | R4: 1 | S4: The uksi walk is a single figure across both SI collections; it has never been split by year. | T4: Split the uksi year walk so each SI collection gets its own denominator. | U4: Most law that binds people is secondary, not primary.
A5: L04 | B5: T1 The law itself | C5: UK Statutory Instruments 2010 to date | D5: si-2010plus | E5: HELD | G5: legislation.gov.uk (TNA) | H5: SI | I5: 100971 | J5: 73558 | K5: =IFERROR(J5/I5,"") -> 0.7285062 | L5: 275744 | M5: 40102967 | N5: MEASURED | O5: ogl-3.0 | P5: CLEAR | Q5: Yes | R5: 1 | S5: Figures are BOTH SI collections combined. 27,413 SIs with text are not held; 8,219 more carry no provisions. | T5: Fetch the 27,413 from the v36 worklist. | U5: As L03.
A6: L05 | B6: T1 The law itself | C6: Retained / assimilated EU law | D6: retained-eu | E6: HELD | G6: legislation.gov.uk (TNA) | H6: instrument | I6: 46150 | J6: 39068 | K6: =IFERROR(J6/I6,"") -> 0.84654388 | L6: 199224 | M6: 18991303 | N6: MEASURED | O6: ogl-3.0+eu-2011-833 | P6: CLEAR | Q6: Yes | R6: 1 | S6: 7,082 instruments with text not held. 113,623 further published instruments carry no provisions. | T6: Fetch the 7,082 from the v36 worklist. | U6: Post-Brexit statute book depends on knowing what was retained.
A7: L06 | B7: T1 The law itself | C7: Devolved primary + secondary legislation (asp, ssi, anaw/asc, wsi, nia, nisr) | D7: regional | E7: HELD | G7: legislation.gov.uk (TNA) | H7: instrument | I7: 38099 | J7: 26150 | K7: =IFERROR(J7/I7,"") -> 0.68636972 | L7: 341093 | M7: 45623780 | N7: MEASURED | O7: ogl-3.0 | P7: CLEAR | Q7: Yes | R7: 1 | S7: Figure is a residual (all types minus ukpga, uksi, eur) — never printed per type. 1,630 recoverable instruments absent. | T7: Split the walk by type; fetch the 1,630. | U7: Three legislatures make law Westminster does not.
A8: L07 | B8: T1 The law itself | C8: Explanatory Notes to Acts | D8: explanatory-notes | E8: HELD | G8: legislation.gov.uk (TNA) | H8: Act with an EN | I8: not walked | L8: 18651 | M8: 9173040 | N8: UNMEASURED | O8: ogl-3.0 | P8: CLEAR | Q8: Yes | R8: 2 | S8: Old target was 410 against 18,651 held — 4,549% — and the email still printed 100% complete. | T8: Walk: count instruments carrying an EN link at source. | U8: ENs state Parliament's intention. Lex leans on them heavily.
A9: L08 | B9: T1 The law itself | C9: Explanatory Memoranda to SIs | D9: explanatory-memoranda | E9: HELD | G9: legislation.gov.uk (TNA) | H9: SI with an EM | I9: not walked | L9: 21984 | M9: 13515324 | N9: UNMEASURED | O9: ogl-3.0 | P9: CLEAR | Q9: Yes | R9: 2 | S9: Old target 5,420 against 21,984 held — 406%. | T9: Walk: count SIs carrying an EM at source. | U9: The only plain-English account of what an SI does.
A10: L09 | B10: T1 The law itself | C10: Impact Assessments | D10: impact-assessments | E10: PARTIAL | G10: legislation.gov.uk (TNA) | H10: impact assessment | I10: 18759 | J10: 18756 | K10: =IFERROR(J10/I10,"") -> 0.99984008 | L10: 18756 | N10: CLAIMED | O10: ogl-3.0 | P10: CLEAR | Q10: Yes | R10: 2 | S10: 3 absent. Provenance of the 18,759 figure unproven. ~1,235 post-legislative review documents sit inside this collection and cannot be separated out. | T10: Fetch 3; prove the denominator; split out post-legislative memoranda. | U10: Evidence base behind each Bill.
A11: L10 | B11: T1 The law itself | C11: Acts of the Parliament of Northern Ireland 1921–1972 | D11: apni | E11: NOT STARTED | G11: legislation.gov.uk (TNA) | H11: Act | I11: not walked | J11: 0 | L11: 0 | N11: NOT STARTED | O11: ogl-3.0 | P11: CLEAR | Q11: Yes | R11: 1 | S11: Nothing held. 2,602 inbound citations in the corpus point at legislation we do not have. | T11: Build the apni seeder. | U11: Cited 2,602 times by law we DO hold — every one of those is a dead link today.
A12: L11 | B12: T1 The law itself | C12: Church Measures | D12: ukcm | E12: NOT STARTED | G12: legislation.gov.uk (TNA) | H12: Measure | I12: not walked | J12: 0 | L12: 0 | N12: NOT STARTED | O12: ogl-3.0 | P12: CLEAR | Q12: Yes | R12: 1 | S12: Nothing held. 6,803 inbound citations point at it. | T12: Build the ukcm seeder. | U12: Measures have the force of an Act. 6,803 dead citations.
A13: L12 | B13: T1 The law itself | C13: Church Instruments | D13: ukci | E13: NOT STARTED | G13: legislation.gov.uk (TNA) | H13: instrument | I13: not walked | J13: 0 | L13: 0 | N13: NOT STARTED | O13: ogl-3.0 | P13: CLEAR | Q13: Yes | R13: 3 | S13: Nothing held. | T13: Build the ukci seeder. | U13: Completes the legislation.gov.uk type list.
A14: L13 | B14: T1 The law itself | C14: Local and Private Acts | D14: ukla | E14: NOT STARTED | G14: legislation.gov.uk (TNA) | H14: Act | I14: not walked | J14: 0 | L14: 0 | N14: NOT STARTED | O14: ogl-3.0 | P14: CLEAR | Q14: Yes | R14: 2 | S14: No target row and no seeder has ever existed. | T14: Create target + seeder. | U14: Ports, railways, universities, City of London — private Acts still bind. Plan estimated ~10,000 sections.
A15: L14 | B15: T1 The law itself | C15: Pre-1801 statute (Statutes of the Realm; Acts of the Parliament of Scotland pre-1707; Irish Acts) | D15: pre-1801-statute | E15: NOT STARTED | F15: NEW | G15: legislation.gov.uk + TNA + BAILII | H15: Act | I15: not walked | J15: 0 | L15: 0 | N15: NOT STARTED | O15: ogl-3.0 | P15: UNVERIFIED | Q15: Unknown | R15: 3 | S15: Not in the plan at all. legislation.gov.uk carries some pre-1801 Acts (Magna Carta, Bill of Rights) but coverage is partial. | T15: Scope what legislation.gov.uk actually holds pre-1801; identify the gap. | U15: Constitutional statutes that are still in force and still argued in court.
A16: L15 | B16: T1 The law itself | C16: Legacy LegislationSection table | D16: legacy-legislation-section | E16: RETIRED | G16: internal | H16: section | J16: 0 | L16: 914274 | N16: LEGACY | O16: ogl-3.0 | P16: CLEAR | Q16: Yes | R16: 1 | S16: 914,274 sections across 127,790 instruments sitting in the old table, reachable by no search path. Overlap with corpus_sections and the worklist has never been joined. | T16: Join legacy ids to corpus_sections and to the worklist; report how many are in NEITHER. That number decides whether this matters at all. | U16: Either a large hidden gap or a large duplicate. Nobody currently knows which.
A17: P01 | B17: T2 Parliament (Westminster) | C17: Hansard — Commons debates (modern) | D17: pwdata-debates | E17: HELD | G17: TheyWorkForYou / ParlParse | H17: sitting-day file | I17: not walked | L17: 6387304 | M17: 1012382550 | N17: UNMEASURED | O17: opl-3.0 | P17: CLEAR | Q17: Yes | R17: 1 | S17: Largest single collection. No publisher walk. Overlaps historic-hansard and is not de-duplicated in retrieval. | T17: Walk the scrapedxml directory index; report missing days. | U17: The record of what Parliament said. Core to every Scrutinise answer.
A18: P02 | B18: T2 Parliament (Westminster) | C18: Hansard — historic (1803–2005) | D18: historic-hansard | E18: HELD | G18: api.parliament.uk historic-hansard | H18: House + date | I18: not walked | L18: 4641085 | M18: 783216544 | N18: UNMEASURED | O18: opl-3.0 | P18: CLEAR | Q18: Yes | R18: 1 | S18: No walk. Known overlap window with pwdata-debates / pwdata-lords, not de-duplicated. | T18: Walk the sittings index; measure and resolve the overlap. | U18: 200 years of debate. Where the intention behind old Acts lives.
A19: P03 | B19: T2 Parliament (Westminster) | C19: Written Answers — Commons | D19: pwdata-wrans | E19: HELD | G19: TheyWorkForYou / ParlParse | H19: sitting-day file | I19: not walked | L19: 1232999 | M19: 180642434 | N19: UNMEASURED | O19: opl-3.0 | P19: CLEAR | Q19: Yes | R19: 2 | S19: No walk. | T19: Walk. | U19: Ministers' own account of how a policy operates.
A20: P04 | B20: T2 Parliament (Westminster) | C20: Hansard — Lords debates | D20: pwdata-lords | E20: HELD | G20: TheyWorkForYou / ParlParse | H20: sitting-day file | I20: not walked | L20: 752805 | M20: 211590640 | N20: UNMEASURED | O20: opl-3.0 | P20: CLEAR | Q20: Yes | R20: 1 | S20: No walk. | T20: Walk. | U20: Where most Bill scrutiny actually happens.
A21: P05 | B21: T2 Parliament (Westminster) | C21: Committee reports | D21: committees-reports | E21: HELD | G21: committees.parliament.uk | H21: publication | I21: not walked | L21: 323922 | M21: 70980271 | N21: UNMEASURED | O21: opl-3.0 | P21: CLEAR | Q21: Yes | R21: 1 | S21: Old target 24,876 against 323,922 held — 1,302% — printed as 100% complete. | T21: Walk the committees publications API. | U21: Select committee reports are the main pre-legislative evidence base.
A22: P06 | B22: T2 Parliament (Westminster) | C22: Westminster Hall debates | D22: pwdata-westminster | E22: HELD | G22: TheyWorkForYou / ParlParse | H22: sitting-day file | I22: not walked | L22: 239262 | M22: 83774185 | N22: UNMEASURED | O22: opl-3.0 | P22: CLEAR | Q22: Yes | R22: 2 | S22: No walk. | T22: Walk. | U22: Backbench debates on emerging issues.
A23: P07 | B23: T2 Parliament (Westminster) | C23: Written Answers — Lords | D23: pwdata-lordswrans | E23: HELD | G23: TheyWorkForYou / ParlParse | H23: sitting-day file | I23: not walked | L23: 175592 | M23: 27526245 | N23: UNMEASURED | O23: opl-3.0 | P23: CLEAR | Q23: Yes | R23: 2 | S23: 1 failed fetch (HTTP 503, retryable). | T23: Walk; retry the failure. | U23: As P03.
A24: P08 | B24: T2 Parliament (Westminster) | C24: Committee oral + written evidence | D24: committees-evidence | E24: HELD | G24: committees.parliament.uk | H24: evidence item | I24: not walked | L24: 140567 | M24: 508343362 | N24: UNMEASURED | O24: opl-3.0 | P24: CLEAR | Q24: Yes | R24: 1 | S24: No walk. | T24: Walk. | U24: The raw testimony behind the reports — often more useful than the report.
A25: P09 | B25: T2 Parliament (Westminster) | C25: Commons oral questions (Linked Data API) | D25: lda-commonsoralquestions | E25: HELD | G25: data.parliament.uk (LDA) | H25: question | I25: not walked | L25: 69529 | M25: 2004846 | N25: UNMEASURED | O25: opl-3.0 | P25: CLEAR | Q25: Yes | R25: 3 | S25: The LDA service is scheduled for retirement. | T25: Confirm the service still answers; plan a migration to the modern API. | U25: Ministerial accountability on the floor.
A26: P10 | B26: T2 Parliament (Westminster) | C26: Early Day Motions | D26: early-day-motions | E26: HELD | G26: edm.parliament.uk | H26: motion | I26: not walked | L26: 60737 | M26: 8085150 | N26: UNMEASURED | O26: opl-3.0 | P26: CLEAR | Q26: Yes | R26: 3 | S26: No walk. | T26: Walk. | U26: Cheap signal of backbench opinion — feeds the position graph.
A27: P11 | B27: T2 Parliament (Westminster) | C27: e-Petitions (open + archived) | D27: petitions | E27: PARTIAL | G27: petition.parliament.uk | H27: petition | I27: not walked | L27: 49529 | M27: 6244101 | N27: UNMEASURED | O27: ogl-3.0 | P27: CLEAR | Q27: Yes | R27: 2 | S27: Internal estimate ~66,075 (75%) — an internal guess, not a publisher figure. | T27: Walk the JSON API for a real denominator. | U27: Direct public demand for legislative change. Central to Scrutinise's mission.
A28: P12 | B28: T2 Parliament (Westminster) | C28: Written Ministerial Statements — Commons | D28: pwdata-wms | E28: HELD | G28: TheyWorkForYou / ParlParse | H28: sitting-day file | I28: not walked | L28: 23863 | M28: 10223233 | N28: UNMEASURED | O28: opl-3.0 | P28: CLEAR | Q28: Yes | R28: 3 | S28: No walk. | T28: Walk. | U28: How policy changes are announced without debate.
... A32: P16 | B32: T2 Parliament (Westminster) | C32: Register of Members' Financial Interests | D32: members-interests | E32: HELD | G32: Parliament interests API | H32: register entry | I32: not walked | L32: 3448 | M32: 42435 | N32: UNMEASURED | O32: opl-3.0 | P32: CLEAR | Q32: Yes | R32: 3 | S32: No walk. | T32: Walk. | U32: Conflict-of-interest context on any position.
A33: P17 | B33: T2 Parliament (Westminster) | C33: Lords division votes (per member) | D33: lords-divisions-votes | E33: HELD | G33: Parliament votes API | H33: division | I33: not walked | L33: 3284 | N33: UNMEASURED | O33: opl-3.0 | P33: CLEAR | Q33: Yes | R33: 2 | S33: Possible duplicate of lda-lordsdivisions. | T33: Walk; resolve duplication. | U33: 2.5M vote edges in the position graph rest on this.
A34: P18 | B34: T2 Parliament (Westminster) | C34: Commons division votes (per member) | D34: commons-divisions-votes | E34: HELD | G34: Parliament votes API | H34: division | I34: not walked | L34: 2361 | N34: UNMEASURED | O34: opl-3.0 | P34: CLEAR | Q34: Yes | R34: 2 | S34: Possible duplicate of lda-commonsdivisions. | T34: Walk; resolve duplication. | U34: As P17.
A35: P19 | B35: T2 Parliament (Westminster) | C35: Lords divisions (Linked Data API) | D35: lda-lordsdivisions | E35: HELD | G35: data.parliament.uk (LDA) | H35: division | I35: not walked | L35: 2089 | M35: 17753 | N35: UNMEASURED | O35: opl-3.0 | P35: CLEAR | Q35: Yes | R35: 3 | S35: Possible duplicate of lords-divisions-votes. | T35: Walk; resolve duplication. | U35: As P17.
A36: P20 | B36: T2 Parliament (Westminster) | C36: Erskine May | D36: erskine-may | E36: PARTIAL | G36: erskinemay.parliament.uk | H36: paragraph | I36: 2038 | J36: 1873 | K36: =IFERROR(J36/I36,"") -> 0.91903827 | L36: 1873 | M36: 589373 | N36: CLAIMED | O36: opl-3.0 | P36: UNVERIFIED | Q36: Unknown | R36: 2 | S36: 165 paragraphs short. Provenance of the 2,038 figure unproven. Access described as 'partial' in the plan. | T36: Finish; prove the denominator; verify the licence. | U36: The rulebook for how Parliament handles a Bill. Directly useful to a reformer.
A37: P21 | B37: T2 Parliament (Westminster) | C37: Written answers (legacy collection) | D37: written-answers | E37: HELD | G37: Parliament API | H37: file | I37: not walked | L37: 143 | M37: 43748825 | N37: UNMEASURED | O37: opl-3.0 | P37: CLEAR | Q37: Yes | R37: 2 | S37: 143 rows at roughly 306,000 words each — whole files stored as single sections. Unretrievable at this granularity. | T37: Re-split into per-answer sections. | U37: Broken, not missing. Fixing it is cheap.
A38: P22 | B38: T2 Parliament (Westminster) | C38: Bill amendment papers, marshalled lists and notices of amendments | D38: bill-amendments | E38: NOT STARTED | F38: NEW | G38: bills.parliament.uk / publications.parliament.uk | H38: amendment paper | I38: not walked | J38: 0 | L38: 0 | N38: NOT STARTED | O38: opl-3.0 | P38: CLEAR | Q38: Yes | R38: 1 | S38: Not in the plan. Bills-api holds stage metadata, not the amendment text. | T38: Create target + seeder from the Bills API publications endpoint. | U38: THE most directly useful missing source for Scrutinise. An amendment is exactly the artefact a user is trying to produce. Without these, Lex cannot show a user what a real amendment looks like or whether theirs has been tried before.
A39: P23 | B39: T2 Parliament (Westminster) | C39: Public Bill Committee evidence | D39: pbc-evidence | E39: NOT STARTED | F39: NEW | G39: committees.parliament.uk | H39: evidence item | I39: not walked | J39: 0 | L39: 0 | N39: NOT STARTED | O39: opl-3.0 | P39: CLEAR | Q39: Yes | R39: 2 | S39: May be partly inside committees-evidence; never separated. | T39: Determine overlap with committees-evidence, then seed the remainder. | U39: Evidence given directly on a live Bill — the highest-value moment to intervene.
A40: P24 | B40: T2 Parliament (Westminster) | C40: Delegated Powers and Regulatory Reform Committee (DPRRC) reports | D40: dprrc | E40: NOT STARTED | F40: NEW | G40: committees.parliament.uk | H40: report | I40: not walked | J40: 0 | L40: 0 | N40: NOT STARTED | O40: opl-3.0 | P40: CLEAR | Q40: Yes | R40: 2 | S40: May be inside committees-reports; never separated. | T40: Separate out as its own collection. | U40: The committee that judges whether a Bill hands Ministers too much power. Core scrutiny doctrine.
A41: P25 | B41: T2 Parliament (Westminster) | C41: Joint Committee on Statutory Instruments (JCSI) + Secondary Legislation Scrutiny Committee (SLSC) reports | D41: si-scrutiny | E41: NOT STARTED | F41: NEW | G41: committees.parliament.uk | H41: report | I41: not walked | J41: 0 | L41: 0 | N41: NOT STARTED | O41: opl-3.0 | P41: CLEAR | Q41: Yes | R41: 2 | S41: May be inside committees-reports; never separated. | T41: Separate out as its own collection. | U41: The only systematic scrutiny SIs receive. Directly answers 'was this SI challenged?'
A42: P26 | B42: T2 Parliament (Westminster) | C42: Command Papers (White Papers, Green Papers, Government responses, treaty CPs) | D42: command-papers | E42: NOT STARTED | F42: NEW | G42: gov.uk + parliament.uk | H42: Command Paper | I42: not walked | J42: 0 | L42: 0 | N42: NOT STARTED | O42: ogl-3.0 | P42: CLEAR | Q42: Yes | R42: 2 | S42: Plan row 38 existed for White/Green Papers but no target row was created. The 175-section govuk-core-docs collection stands in for this and three other plan rows. | T42: Create a proper command-papers collection; walk the numbered CP series. | U42: A numbered, complete official series. The policy intention behind almost every Bill.
A43: P27 | B43: T2 Parliament (Westminster) | C43: House of Commons Library briefings | D43: commons-library | E43: NOT STARTED | G43: commonslibrary.parliament.uk | H43: briefing | I43: not walked | J43: 0 | L43: 0 | N43: NOT STARTED | O43: opl-3.0 | P43: CLEAR | Q43: Yes | R43: 2 | S43: Plan row 39; no target row ever created. | T43: Create target + seeder. | U43: Neutral, expert, plain-English summaries of every Bill. The single best explanatory layer available.
A44: P28 | B44: T2 Parliament (Westminster) | C44: Select committee correspondence (letters to and from Ministers) | D44: committee-correspondence | E44: NOT STARTED | F44: NEW | G44: committees.parliament.uk | H44: letter | I44: not walked | J44: 0 | L44: 0 | N44: NOT STARTED | O44: opl-3.0 | P44: CLEAR | Q44: Yes | R44: 3 | S44: Not in the plan. | T44: Create target + seeder. | U44: Where commitments get made and chased between reports.
A45: P29 | B45: T2 Parliament (Westminster) | C45: Legislative Consent Motions (Sewel) | D45: legislative-consent | E45: NOT STARTED | F45: NEW | G45: Holyrood / Senedd / NI Assembly | H45: motion | I45: not walked | J45: 0 | L45: 0 | N45: NOT STARTED | O45: OPL / OGL | P45: UNVERIFIED | Q45: Unknown | R45: 3 | S45: Not in the plan. | T45: Create target + seeder across the three legislatures. | U45: Answers 'can Westminster legislate here?' — a question every UK reformer hits.
A46: P30 | B46: T2 Parliament (Westminster) | C46: Regulatory Policy Committee opinions on impact assessments | D46: rpc-opinions | E46: NOT STARTED | F46: NEW | G46: gov.uk | H46: opinion | I46: not walked | J46: 0 | L46: 0 | N46: NOT STARTED | O46: ogl-3.0 | P46: CLEAR | Q46: Yes | R46: 3 | S46: Not in the plan. | T46: Create target + seeder. | U46: Independent verdict on whether a Bill's evidence base holds up.
A47: C01 | B47: T3 Courts & tribunals | C47: Employment Tribunal decisions (2017–) | D47: et-decisions | E47: HELD | G47: gov.uk employment-tribunal-decisions | H47: decision | I47: not walked | L47: 293399 | M47: 291435626 | N47: UNMEASURED | O47: ogl-3.0 | P47: CLEAR | Q47: Yes | R47: 1 | S47: 131,654 of 293,403 rows (44.9%) are a landing page, not a decision — median 18 words. They are counted as content and compete with real decisions in search. | T47: DECIDED 23 Aug: delete the 131,654 and re-fetch the real decisions. | U47: Employment law is where most people meet the legal system.
A48: C02 | B48: T3 Courts & tribunals | C48: Find Case Law — senior courts (2001–) | D48: tna-caselaw | E48: HELD | G48: caselaw.nationalarchives.gov.uk | H48: judgment | I48: not walked | L48: 74896 | M48: 680711377 | N48: UNMEASURED | O48: ojl-2.0 | P48: ACTION — Charlie letter | Q48: No | R48: 1 | S48: 12.7% of all embedded case-law text is stylesheet markup; chunk 0 is >50% markup in 77% of judgments. Open Justice Licence v2.0 EXCLUDES computational analysis — our bulk ingest and FTS index are outside the licence as it stands. | T48: Strip stylesheet and re-embed chunk 0 (~$31 on the batch endpoint). CHARLIE: apply for TNA's computational-analysis licence. | U48: Modern binding authority.
A49: C03 | B49: T3 Courts & tribunals | C49: Case law before 2001 (BAILII) | D49: bailii-pre-2001 | E49: NOT STARTED | G49: bailii.org | H49: judgment | I49: not walked | J49: 0 | L49: 0 | N49: NOT STARTED | O49: BAILII terms | P49: ACTION — Charlie letter | Q49: Unknown | R49: 1 | S49: LARGEST KNOWN GAP. All four bailii-* targets were retired as 'superseded by tna-caselaw' — but tna-caselaw starts in 2001, so nothing superseded them. Plan estimate of 2,000,000 sections is unverified and the unit is ambiguous. | T49: DECIDED 23 Aug: walk BAILII per court per decade to size it, then fetch. CHARLIE: agree terms with BAILII (a charity) before a bulk run. | U49: Every leading authority before 2001 — Donoghue v Stevenson, Pepper v Hart, the whole common law. Without it the corpus cannot answer a legal question properly.
A50: C04 | B50: T3 Courts & tribunals | C50: Scottish court judgments | D50: scottish-courts | E50: PARTIAL | G50: scotcourts.gov.uk | H50: judgment | I50: 13070 | J50: 13056 | K50: =IFERROR(J50/I50,"") -> 0.99892884 | L50: 13056 | M50: 80067110 | N50: CLAIMED | O50: pending-verification | P50: UNVERIFIED | Q50: Unknown | R50: 2 | S50: 14 short. Provenance of the 13,070 figure unproven. | T50: Finish; prove the denominator; verify the licence. | U50: Separate legal system.
A51: C05 | B51: T3 Courts & tribunals | C51: Tax tribunals (FTT + Upper Tribunal Tax Chamber) | D51: tax-tribunals | E51: HELD | G51: TNA / HMCTS feeds | H51: decision | I51: not walked | L51: 12089 | M51: 71631645 | N51: UNMEASURED | O51: pending-verification | P51: UNVERIFIED | Q51: Unknown | R51: 2 | S51: No licence statement found on the HMCTS legacy site. | T51: Walk; verify the licence. | U51: Tax is the densest area of live legal dispute.
A52: C06 | B52: T3 Courts & tribunals | C52: Northern Ireland judgments | D52: ni-judgments | E52: HELD | G52: judiciaryni.uk | H52: judgment | I52: not walked | L52: 7772 | M52: 40857928 | N52: UNMEASURED | O52: pending-verification | P52: UNVERIFIED | Q52: Unknown | R52: 2 | S52: © Crown asserted, no open licence stated. Listing budget is ~30 pages per IP session. | T52: Walk; verify the licence. | U52: Separate legal system.
A53: C07 | B53: T3 Courts & tribunals | C53: ECtHR judgments (UK respondent) | D53: echr-hudoc | E53: HELD | G53: hudoc.echr.coe.int | H53: judgment | I53: not walked | L53: 4410 | M53: 17991627 | N53: UNMEASURED | O53: echr-nc | P53: RESTRICTED | Q53: No | R53: 2 | S53: Free reproduction for private/information/education only; commercial use requires prior written permission. Default-excluded from any commercial surface. | T53: Walk with respondent=GBR. CHARLIE: write for commercial permission if a commercial arm is planned. | U53: Human Rights Act cases turn on Strasbourg authority.
A54: C08 | B54: T3 Courts & tribunals | C54: First-tier and Upper Tribunal decisions (all chambers other than ET and Tax) | D54: tribunals-other | E54: NOT STARTED | F54: NEW | G54: gov.uk / Find Case Law | H54: decision | I54: not walked | J54: 0 | L54: 0 | N54: NOT STARTED | O54: ogl-3.0 / ojl-2.0 | P54: ACTION — Charlie letter | Q54: Unknown | R54: 1 | S54: Not in the plan. Immigration & Asylum, Social Entitlement, Property, General Regulatory, Health Education & Social Care, War Pensions. | T54: Create targets + seeders per chamber. | U54: Tribunals decide far more cases than the courts and are where welfare, immigration and housing law is actually applied.
A55: C09 | B55: T3 Courts & tribunals | C55: Coroners' Prevention of Future Deaths reports and responses | D55: pfd-reports | E55: NOT STARTED | F55: NEW | G55: judiciary.uk | H55: report | I55: ~6,000 | J55: 0 | L55: 0 | N55: NOT STARTED | O55: ogl-3.0 | P55: UNVERIFIED | Q55: Unknown | R55: 1 | S55: Not in the plan. ~5,891 reports as at Sept 2025, plus the statutory responses; ~713 new reports in 2024 alone. Full text published on webpages since Jan 2023; earlier ones are PDFs. | T55: Create target + seeder; PDF extraction needed for pre-2023. | U55: A coroner naming a legal or regulatory failure and demanding change is the purest legislative-reform trigger in the system. Small volume, exceptionally high signal for Scrutinise's mission.
A56: C10 | B56: T3 Courts & tribunals | C56: Sentencing remarks | D56: sentencing-remarks | E56: NOT STARTED | F56: NEW | G56: judiciary.uk | H56: remarks | I56: not walked | J56: 0 | L56: 0 | N56: NOT STARTED | O56: pending-verification | P56: UNVERIFIED | Q56: Unknown | R56: 3 | S56: Not in the plan. | T56: Create target + seeder. | U56: Shows how sentencing guidelines land in practice.
A57: C11 | B57: T3 Courts & tribunals | C57: CJEU case law (pre-Brexit retained authority) | D57: cjeu | E57: NOT STARTED | F57: NEW | G57: curia.europa.eu / EUR-Lex | H57: judgment | I57: not walked | J57: 0 | L57: 0 | N57: NOT STARTED | O57: eu-2011-833 | P57: CLEAR | Q57: Yes | R57: 2 | S57: Not in the plan as a separate collection. Some may be inside eur-lex. | T57: Determine overlap with eur-lex, then seed the remainder. | U57: Retained EU case law still binds UK courts unless departed from. Currently unanswerable.
A58: C12 | B58: T3 Courts & tribunals | C58: Leading cases (curated subset) | D58: leading-cases | E58: NOT STARTED | G58: BAILII / TNA subset | H58: judgment | I58: not walked | J58: 0 | L58: 0 | N58: NOT STARTED | O58: ojl-2.0 | P58: ACTION — Charlie letter | Q58: Unknown | R58: 3 | S58: Plan row 44; never built. | T58: Derive from C03 once held, rather than fetching separately. | U58: A curated spine improves ranking more than raw volume.
A59: D01 | B59: T4 Devolved legislatures | C59: Scottish Parliament Official Report | D59: scottish-parliament-or | E59: HELD | G59: parliament.scot | H59: meeting | I59: not walked | L59: 1043264 | M59: 124396770 | N59: UNMEASURED | O59: Scottish Parliament OPL | P59: UNVERIFIED | Q59: Unknown | R59: 1 | S59: Absent from the Corpus Plan entirely — 1.04M sections the workbook did not know existed. | T59: Add plan row; walk the Official Report index; verify the licence. | U59: Holyrood makes law in devolved areas. Currently unmeasured.
A60: D02 | B60: T4 Devolved legislatures | C60: NI Assembly Hansard (2012–) | D60: niassembly-hansard | E60: HELD | G60: aims.niassembly.gov.uk | H60: sitting | I60: not walked | L60: 196348 | M60: 32837622 | N60: UNMEASURED | O60: NI Assembly OPL | P60: UNVERIFIED | Q60: Unknown | R60: 1 | S60: Absent from the Corpus Plan. Starts 2012 — earlier Assembly and pre-1972 Stormont record not held. | T60: Add plan row; walk; scope the pre-2012 record. | U60: Charlie's own jurisdiction. Also the corpus with the largest inbound-citation gap (apni).
A61: D03 | B61: T4 Devolved legislatures | C61: Senedd Cofnod / Record of Proceedings | D61: senedd-cofnod | E61: HELD | G61: record.senedd.wales | H61: meeting | I61: not walked | L61: 191730 | M61: 29294355 | N61: UNMEASURED | O61: ogl-3.0 | P61: CLEAR | Q61: Yes | R61: 1 | S61: Absent from the Corpus Plan. 61.1% of 191,730 speeches carry an inherited (wrong) heading. ~95% of a 40-row sample had Welsh-language bodies, which are effectively unaskable through an English-language search. | T61: Fix heading inheritance in the shared parser. CHARLIE DECISION: Welsh-language strategy — translate, embed bilingually, or label and exclude. | U61: Wales legislates bilingually and both texts are authoritative.
A62: D04 | B62: T4 Devolved legislatures | C62: Scottish Government and Welsh Government statutory guidance | D62: devolved-guidance | E62: NOT STARTED | F62: NEW | G62: gov.scot / gov.wales | H62: guidance | I62: not walked | J62: 0 | L62: 0 | N62: NOT STARTED | O62: OGL | P62: CLEAR | Q62: Yes | R62: 2 | S62: Not in the plan. We hold devolved legislation but none of the guidance that operates it. | T62: Create targets + seeders. | U62: An asp without its guidance is half the picture.
A63: G01 | B63: T5 Government, regulators & guidance | C63: Arm's-length bodies on GOV.UK (quangos) | D63: quangos-govuk | E63: PARTIAL | G63: gov.uk Content API | H63: document | I63: 162004 | L63: 171030 | M63: 902984511 | N63: UNMEASURED | O63: ogl-3.0 | P63: CLEAR | Q63: Yes | R63: 1 | S63: 1,255 organisations enumerated (see Quangos tab): 348 live, 590 closed, 300 exempt (they publish on their OWN sites, not gov.uk), 16 joining. 162,004 relevant documents identified on gov.uk. The 300 exempt bodies' own-site content has never been scoped and includes the Bank of England, CQC, Civil Aviation Authority, Environment Agency and the BBC. | T63: Reconcile held sections against the 162,004; then scope the 300 exempt bodies' own sites as a separate wave. | U63: This is how legislation is actually operated day to day. The single largest unmeasured body of guidance.
A64: G02 | B64: T5 Government, regulators & guidance | C64: HMRC technical manuals | D64: hmrc-manuals | E64: PARTIAL | G64: gov.uk | H64: manual page | I64: not walked | L64: 69136 | M64: 20775736 | N64: UNMEASURED | O64: ogl-3.0 | P64: CLEAR | Q64: Yes | R64: 1 | S64: Plan guessed 500,000 sections; 69,136 held (13.8% of a guess). No walk. | T64: Walk the manuals A–Z and each contents tree; then backfill. | U64: Tax is Scrutinise's likeliest commercial fork. HMRC manuals are the IBFD replacement.
A65: G03 | B65: T5 Government, regulators & guidance | C65: ICO decisions and enforcement | D65: ico | E65: PARTIAL | G65: ico.org.uk | H65: decision notice | I65: 26576 | J65: 26562 | K65: =IFERROR(J65/I65,"") -> 0.99947321 | L65: 26562 | M65: 63079776 | N65: CLAIMED | O65: ogl-3.0 | P65: CLEAR | Q65: Yes | R65: 2 | S65: 14 short; provenance unproven. | T65: Finish; prove the denominator. | U65: FOI and data-protection decisions cited constantly.
A66: G04 | B66: T5 Government, regulators & guidance | C66: CMA cases and merger decisions | D66: cma-cases | E66: PARTIAL | G66: gov.uk CMA | H66: case | I66: 22898 | J66: 21525 | K66: =IFERROR(J66/I66,"") -> 0.94003843 | L66: 21525 | M66: 157997549 | N66: CLAIMED | O66: ogl-3.0 | P66: CLEAR | Q66: Yes | R66: 2 | S66: 94% of an INTERNAL estimate, not a publisher figure. | T66: Finish; walk for a real denominator. | U66: Competition decisions drive market regulation.
A67: G05 | B67: T5 Government, regulators & guidance | C67: Ofgem | D67: ofgem | E67: HELD | G67: ofgem.gov.uk | H67: document | I67: not walked | L67: 17143 | M67: 54974878 | N67: UNMEASURED | O67: ogl-3.0 | P67: CLEAR | Q67: Yes | R67: 2 | S67: No walk. | T67: Walk. | U67: Energy regulation.
A68: G06 | B68: T5 Government, regulators & guidance | C68: HMRC codes and guidance | D68: hmrc-codes-guidance | E68: HELD | G68: gov.uk | H68: document | I68: not walked | L68: 14067 | M68: 11735393 | N68: UNMEASURED | O68: ogl-3.0 | P68: CLEAR | Q68: Yes | R68: 2 | S68: No walk. | T68: Walk.
A69: G07 | B69: T5 Government, regulators & guidance | C69: Government consultations | D69: consultations | E69: HELD | G69: gov.uk consultation hub | H69: consultation | I69: not walked | L69: 7448 | N69: UNMEASURED | O69: ogl-3.0 | P69: CLEAR | Q69: Yes | R69: 2 | S69: No walk. Consultation OUTCOMES and government responses may be under-captured. | T69: Walk; separate outcomes from launches. | U69: A live consultation is the cheapest moment for a reformer to intervene.
A70: G08 | B70: T5 Government, regulators & guidance | C70: Ofcom | D70: ofcom | E70: HELD | G70: ofcom.org.uk | H70: document | I70: not walked | L70: 4169 | M70: 11903554 | N70: UNMEASURED | O70: ogl-3.0 | P70: CLEAR | Q70: Yes | R70: 2 | S70: No walk. | T70: Walk. | U70: Communications regulation.
A71: G09 | B71: T5 Government, regulators & guidance | C71: FCA Handbook | D71: fca-handbook | E71: PARTIAL | G71: fca.org.uk Handbook | H71: provision | I71: not walked | L71: 3661 | M71: 3014148 | N71: UNMEASURED | O71: fca-restricted | P71: ACTION — Charlie letter | Q71: No | R71: 1 | S71: Plan guessed 150,000; 3,661 held (2.4% of a guess). Reproduction or storage in a retrieval system requires the FCA's prior written permission and a licence agreement — we are storing it now. | T71: CHARLIE: write to the FCA for a Handbook licence BEFORE any backfill. Then walk and backfill. | U71: Financial services rulebook. Commercially the most valuable single corpus we could hold.
A72: G10 | B72: T5 Government, regulators & guidance | C72: NAO reports | D72: nao-reports | E72: HELD | G72: nao.org.uk | H72: report | I72: not walked | L72: 2570 | M72: 25566539 | N72: UNMEASURED | O72: nao-nc | P72: RESTRICTED | Q72: No | R72: 2 | S72: Free re-use NON-COMMERCIAL with attribution; commercial requires express permission. | T72: Walk. CHARLIE: write to the NAO if a commercial arm is planned. | U72: Post-implementation evidence on whether legislation worked.
A73: G11 | B73: T5 Government, regulators & guidance | C73: HMRC Tax Information and Impact Notes | D73: hmrc-tiins | E73: HELD | G73: gov.uk | H73: TIIN | I73: not walked | L73: 791 | M73: 145223 | N73: UNMEASURED | O73: ogl-3.0 | P73: CLEAR | Q73: Yes | R73: 3 | S73: No walk. | T73: Walk.
A74: G12 | B74: T5 Government, regulators & guidance | C74: Independent reviews and audits | D74: independent-reviews | E74: PARTIAL | G74: gov.uk + own domains | H74: review | I74: not walked | L74: 657 | M74: 17191906 | N74: UNMEASURED | O74: ogl-3.0 | P74: CLEAR | Q74: Yes | R74: 3 | S74: No walk. | T74: Walk.
A75: G13 | B75: T5 Government, regulators & guidance | C75: Office of Tax Simplification reports | D75: ots-reports | E75: HELD | G75: gov.uk | H75: report | I75: not walked | L75: 497 | M75: 369741 | N75: UNMEASURED | O75: ogl-3.0 | P75: CLEAR | Q75: Yes | R75: 3 | S75: OTS abolished 2023 — collection is closed and complete by definition. | T75: Confirm closure; mark COMPLETE-CLOSED.
A76: G14 | B76: T5 Government, regulators & guidance | C76: HMRC ancillary material | D76: hmrc-ancillary | E76: HELD | G76: gov.uk | H76: document | I76: not walked | L76: 472 | M76: 1044360 | N76: UNMEASURED | O76: ogl-3.0 | P76: CLEAR | Q76: Yes | R76: 3 | S76: No walk. | T76: Walk.
A77: G15 | B77: T5 Government, regulators & guidance | C77: College of Policing Authorised Professional Practice | D77: college-of-policing | E77: PARTIAL | G77: college.police.uk | H77: APP page | I77: not walked | L77: 332 | M77: 840308 | N77: UNMEASURED | O77: pending-verification | P77: UNVERIFIED | Q77: Unknown | R77: 1 | S77: Plan guessed 8,000; 332 held (4.2% of a guess). Terms and conditions page is Cloudflare-blocked so the licence is unverified. | T77: Walk the APP tree; verify licence by contacting the College directly. | U77: Police powers guidance — how criminal law is actually exercised. Charlie asked for this specifically.
A78: G16 | B78: T5 Government, regulators & guidance | C78: CPS prosecution guidance | D78: cps-guidance | E78: HELD | G78: cps.gov.uk | H78: guidance page | I78: not walked | L78: 270 | M78: 1272877 | N78: UNMEASURED | O78: ogl-3.0 | P78: CLEAR | Q78: Yes | R78: 2 | S78: No walk. 270 sections looks low for the full Legal Guidance set. | T78: Walk. | U78: Charging decisions — the operational face of criminal law.
A79: G17 | B79: T5 Government, regulators & guidance | C79: Sentencing Council guidelines | D79: sentencing-council | E79: PARTIAL | G79: sentencingcouncil.org.uk | H79: guideline | I79: not walked | L79: 253 | M79: 1496124 | N79: UNMEASURED | O79: ogl-3.0 | P79: CLEAR | Q79: Yes | R79: 2 | S79: Plan guessed 2,000; 253 held (12.7% of a guess). Attribution must include the source-document title (row-specific). | T79: Walk; backfill.
A80: G18 | B80: T5 Government, regulators & guidance | C80: PACE Codes, Civil Service Code, Ministerial Code, Cabinet Manual, Green and Magenta Books, White Papers | D80: govuk-core-docs | E80: PARTIAL | G80: gov.uk | H80: document | I80: not walked | L80: 175 | M80: 3058430 | N80: UNMEASURED | O80: ogl-3.0 | P80: CLEAR | Q80: Yes | R80: 1 | S80: ONE 175-section collection standing in for FOUR separate plan rows (18, 19, 20, 38) estimated at 1,800+ sections combined. Nothing here can be reported on separately. | T80: SPLIT into: pace-codes, civil-service-codes, treasury-guidance, white-papers. Then walk each. | U80: Charlie asked specifically for police and civil service codes. They are technically 'held' but indistinguishably mixed and almost certainly incomplete.
A81: G19 | B81: T5 Government, regulators & guidance | C81: Public inquiry reports | D81: inquiry-reports | E81: HELD | G81: individual inquiry sites | H81: report | I81: not walked | L81: 140 | M81: 14560013 | N81: UNMEASURED | O81: ogl-3.0 | P81: CLEAR | Q81: Yes | R81: 1 | S81: 140 sections is implausibly low against the major inquiries alone. | T81: Walk the public inquiries register. | U81: Grenfell, Covid-19, Infected Blood, Post Office/Horizon, IICSA — each produced direct legislative recommendations.
A82: G20 | B82: T5 Government, regulators & guidance | C82: Public inquiry evidence and transcripts | D82: inquiry-evidence | E82: PARTIAL | G82: individual inquiry sites | H82: evidence item | I82: not walked | L82: 89 | M82: 1130004 | N82: UNMEASURED | O82: ogl-3.0 | P82: CLEAR | Q82: Yes | R82: 1 | S82: 89 sections held. The Covid-19 and Grenfell inquiries alone published tens of thousands of pages of transcript and exhibits. | T82: Walk each live inquiry's evidence index separately. | U82: Transcripts contain the reasoning that reports only summarise.
A83: G21 | B83: T5 Government, regulators & guidance | C83: Local Government and Social Care Ombudsman decisions | D83: lgsco | E83: PARTIAL | G83: lgo.org.uk | H83: decision | I83: not walked | L83: 40 | M83: 14772 | N83: UNMEASURED | O83: ogl-3.0 | P83: UNVERIFIED | Q83: Unknown | R83: 2 | S83: 40 sections held. The published denominator is likely tens of thousands, not the ~100 recorded internally. 1 failed fetch. | T83: Walk; retry the failure; verify the licence. | U83: How councils apply statutory duties in practice.
A84: G22 | B84: T5 Government, regulators & guidance | C84: Building Regulations Approved Documents | D84: building-regs | E84: PARTIAL | G84: gov.uk | H84: Approved Document | I84: ~15 | J84: 21 | L84: 21 | M84: 9369 | N84: UNMEASURED | O84: ogl-3.0 | P84: CLEAR | Q84: Yes | R84: 1 | S84: 21 rows at ~446 words each. Approved Documents run to tens of thousands of words each — the PDF text is not being captured. | T84: Fix PDF extraction, then re-fetch. | U84: Post-Grenfell this is one of the most actively reformed areas of law. Currently effectively empty.
A85: G23 | B85: T5 Government, regulators & guidance | C85: Planning policy (NPPF, PPG) | D85: planning-policy | E85: PARTIAL | G85: gov.uk | H85: policy document | I85: not walked | L85: 64 | M85: 292155 | N85: UNMEASURED | O85: ogl-3.0 | P85: CLEAR | Q85: Yes | R85: 1 | S85: Plan guessed 5,000; 64 held (1.3% of a guess). | T85: Walk; backfill. | U85: Planning is the single most common subject of local legislative complaint.
A86: G24 | B86: T5 Government, regulators & guidance | C86: Ofwat | D86: ofwat | E86: NOT STARTED | G86: ofwat.gov.uk | H86: document | I86: not walked | J86: 0 | L86: 0 | N86: NOT STARTED | O86: ogl-3.0 | P86: CLEAR | Q86: Yes | R86: 2 | S86: Named in plan row 26 but never seeded — no target row. | T86: Create target + seeder. | U86: Water regulation; currently a live political issue.
A87: G25 | B87: T5 Government, regulators & guidance | C87: Ofsted | D87: ofsted | E87: NOT STARTED | G87: gov.uk Ofsted | H87: report / framework | I87: not walked | J87: 0 | L87: 0 | N87: NOT STARTED | O87: ogl-3.0 | P87: CLEAR | Q87: Yes | R87: 2 | S87: Named in plan row 26 but never seeded. | T87: Create target + seeder. | U87: Education inspection framework and reports.
A88: G26 | B88: T5 Government, regulators & guidance | C88: NHS England guidance and standard contracts | D88: nhs-guidance | E88: NOT STARTED | G88: england.nhs.uk | H88: document | I88: not walked | J88: 0 | L88: 0 | N88: NOT STARTED | O88: ogl-3.0 | P88: CLEAR | Q88: Yes | R88: 2 | S88: Plan row 22 (20,000 sections estimated); no target row ever created. | T88: Create target + seeder. | U88: NHS operates under a vast body of quasi-statutory guidance.
A89: G27 | B89: T5 Government, regulators & guidance | C89: Health and Safety Executive — Approved Codes of Practice and guidance | D89: hse | E89: NOT STARTED | F89: NEW | G89: hse.gov.uk | H89: ACOP / guidance | I89: not walked | J89: 0 | L89: 0 | N89: NOT STARTED | O89: ogl-3.0 | P89: CLEAR | Q89: Yes | R89: 2 | S89: Not in the plan. ACOPs have special legal status: failure to comply is evidence of breach. | T89: Create target + seeder. | U89: Statutory codes with evidential force — legally more than guidance.
A90: G28 | B90: T5 Government, regulators & guidance | C90: Equality and Human Rights Commission statutory codes and guidance | D90: ehrc | E90: NOT STARTED | F90: NEW | G90: equalityhumanrights.com | H90: code / guidance | I90: not walked | J90: 0 | L90: 0 | N90: NOT STARTED | O90: ogl-3.0 | P90: UNVERIFIED | Q90: Unknown | R90: 2 | S90: Not in the plan. EHRC codes of practice are admissible in evidence under the Equality Act 2010. | T90: Create target + seeder. | U90: Statutory codes with evidential force.
A91: G29 | B91: T5 Government, regulators & guidance | C91: Electoral Commission guidance and reports | D91: electoral-commission | E91: NOT STARTED | F91: NEW | G91: electoralcommission.org.uk | H91: document | I91: not walked | J91: 0 | L91: 0 | N91: NOT STARTED | O91: ogl-3.0 | P91: UNVERIFIED | Q91: Unknown | R91: 2 | S91: Not in the plan. | T91: Create target + seeder. | U91: Election law — directly relevant to a civic-tech platform's own credibility and to a large class of reform proposals.
A92: G30 | B92: T5 Government, regulators & guidance | C92: Charity Commission guidance and statutory inquiry reports | D92: charity-commission | E92: NOT STARTED | F92: NEW | G92: gov.uk | H92: guidance / inquiry | I92: not walked | J92: 0 | L92: 0 | N92: NOT STARTED | O92: ogl-3.0 | P92: CLEAR | Q92: Yes | R92: 3 | S92: Not in the plan. | T92: Create target + seeder. | U92: Scrutinise is itself a not-for-profit; also a large regulated sector.
A93: G31 | B93: T5 Government, regulators & guidance | C93: Financial Ombudsman Service decisions | D93: fos-decisions | E93: NOT STARTED | F93: NEW | G93: financial-ombudsman.org.uk | H93: decision | I93: not walked (large — likely 400,000+) | J93: 0 | L93: 0 | N93: NOT STARTED | O93: unknown | P93: ACTION — Charlie letter | Q93: Unknown | R93: 2 | S93: Not in the plan. FOS publishes final decisions in a searchable database — one of the largest bodies of applied consumer-law reasoning in the UK. | T93: Scope volume and licence first; this could be larger than every regulator combined. | U93: Shows how financial regulation is applied to individuals. Commercially valuable.
A94: G32 | B94: T5 Government, regulators & guidance | C94: Parliamentary and Health Service Ombudsman + Housing Ombudsman decisions | D94: ombudsmen-other | E94: NOT STARTED | F94: NEW | G94: ombudsman.org.uk / housing-ombudsman.org.uk | H94: decision | I94: not walked | J94: 0 | L94: 0 | N94: NOT STARTED | O94: unknown | P94: ACTION — Charlie letter | Q94: Unknown | R94: 3 | S94: Not in the plan. | T94: Scope volume and licence. | U94: Maladministration findings against public bodies.
A95: G33 | B95: T5 Government, regulators & guidance | C95: Pensions Regulator, Ofqual, ORR, Civil Aviation Authority, Payment Systems Regulator, Gambling Commission, Food Standards Agency, MHRA, NICE, CQC, Companies House, IPO | D95: regulators-wave-2 | E95: NOT STARTED | F95: NEW | G95: individual regulator sites | H95: document | I95: not walked | J95: 0 | L95: 0 | N95: NOT STARTED | O95: mixed | P95: UNVERIFIED | Q95: Unknown | R95: 2 | S95: None of these are in the plan. Several are among the 300 GOV.UK-exempt bodies and publish only on their own domains. | T95: Create one target per regulator; walk each. Sequence after the quango exempt-body scope (G01). | U95: Charlie asked for 'all regulators'. This row is the honest statement that most of them are absent.
A96: G34 | B96: T5 Government, regulators & guidance | C96: Legal services regulators (SRA, BSB, Legal Services Board, CILEx) | D96: legal-regulators | E96: NOT STARTED | F96: NEW | G96: individual sites | H96: handbook / decision | I96: not walked | J96: 0 | L96: 0 | N96: NOT STARTED | O96: unknown | P96: UNVERIFIED | Q96: Unknown | R96: 3 | S96: Not in the plan. | T96: Scope. | U96: If Scrutinise forks a commercial legal-services arm, these govern what it may do.
A97: G35 | B97: T5 Government, regulators & guidance | C97: Prudential Regulation Authority rulebook (Bank of England) | D97: pra-rulebook | E97: NOT STARTED | F97: NEW | G97: prarulebook.co.uk | H97: provision | I97: not walked | J97: 0 | L97: 0 | N97: NOT STARTED | O97: unknown | P97: ACTION — Charlie letter | Q97: Unknown | R97: 2 | S97: Not in the plan. The PRA rulebook is the other half of UK financial regulation alongside the FCA Handbook. | T97: Scope volume and licence. | U97: Completes the financial-services picture with the FCA Handbook.
A98: G36 | B98: T5 Government, regulators & guidance | C98: IOPC investigation reports and learning recommendations | D98: iopc | E98: NOT STARTED | F98: NEW | G98: policeconduct.gov.uk | H98: report | I98: not walked | J98: 0 | L98: 0 | N98: NOT STARTED | O98: ogl-3.0 | P98: UNVERIFIED | Q98: Unknown | R98: 3 | S98: Not in the plan. | T98: Create target + seeder. | U98: Police accountability; pairs with College of Policing APP.
A99: G37 | B99: T5 Government, regulators & guidance | C99: Committee on Standards in Public Life reports; ACOBA; Commissioner for Standards | D99: standards-bodies | E99: NOT STARTED | F99: NEW | G99: gov.uk / parliament.uk | H99: report | I99: not walked | J99: 0 | L99: 0 | N99: NOT STARTED | O99: ogl-3.0 / opl-3.0 | P99: CLEAR | Q99: Yes | R99: 3 | S99: Not in the plan. | T99: Create target + seeder. | U99: Constitutional and ethical standards — a recurring subject of reform proposals.
A100: G38 | B100: T5 Government, regulators & guidance | C100: Statutory guidance issued under named Acts (Keeping Children Safe in Education, Working Together, etc.) | D100: statutory-guidance-named | E100: NOT STARTED | F100: NEW | G100: gov.uk | H100: guidance document | I100: not walked | J100: 0 | L100: 0 | N100: NOT STARTED | O100: ogl-3.0 | P100: CLEAR | Q100: Yes | R100: 2 | S100: Not separately identified. Some may be inside quangos-govuk. Statutory guidance carries a legal duty to 'have regard'. | T100: Identify the statutory-guidance document type on gov.uk (1,761 documents flagged in the quango census) and split it into its own collection. | U100: 'Statutory guidance' has a different legal weight to ordinary guidance and must be labelled as such in retrieval.
A101: E01 | B101: T6 EU & international | C101: EUR-Lex | D101: eur-lex | E101: HELD | G101: eur-lex.europa.eu | H101: document | I101: not walked | L101: 241571 | M101: 159379976 | N101: UNMEASURED | O101: eu-2011-833 | P101: CLEAR | Q101: Yes | R101: 2 | S101: Old target 90,260 against 241,571 held — 268% — printed as 100% complete. | T101: Walk the CELLAR sitemap. | U101: Retained EU law needs its EU source text.
A102: E02 | B102: T6 EU & international | C102: UK treaties (FCDO Treaties Online) | D102: uk-treaties-fcdo | E102: HELD | G102: gov.uk FCDO | H102: treaty | I102: not walked | L102: 23372 | M102: 72684947 | N102: UNMEASURED | O102: ogl-3.0 | P102: CLEAR | Q102: Yes | R102: 3 | S102: Possible overlap with uk-treaties. | T102: Walk; resolve overlap.
A103: E03 | B103: T6 EU & international | C103: UK treaties | D103: uk-treaties | E103: HELD | G103: gov.uk | H103: treaty | I103: not walked | L103: 3250 | M103: 34812418 | N103: UNMEASURED | O103: ogl-3.0 | P103: CLEAR | Q103: Yes | R103: 3 | S103: Possible duplicate of uk-treaties-fcdo. | T103: Walk; resolve overlap.
...

Sheet Coverage Summary
A1: COVERAGE SUMMARY
A2: Every figure below is a live formula over the Master Register tab. Change a number there and this updates.
A4: PART 1 — THE ONE THING WE CAN PROVE: UK LEGISLATION
A6: Category | B6: Held | C6: Published | D6: No text at source | E6: Denominator with text | F6: % of all published | G6: % of those with text
A7: UK Public General Acts, 2000 to date | B7: 933 | C7: 938 | D7: 0 | E7: =C7-D7 -> 938 | F7: =B7/C7 -> 0.99466951 | G7: =IFERROR(B7/E7,"") -> 0.99466951
A8: UK Public General Acts, 1801–1999 | B8: 3560 | C8: 16622 | D8: 7279 | E8: =C8-D8 -> 9343 | F8: =B8/C8 -> 0.21417399 | G8: =IFERROR(B8/E8,"") -> 0.38103393
A9: UK Statutory Instruments, all years | B9: 73558 | C9: 109190 | D9: 8219 | E9: =C9-D9 -> 100971 | F9: =B9/C9 -> 0.67366975 | G9: =IFERROR(B9/E9,"") -> 0.7285062
A10: Retained / assimilated EU law | B10: 39068 | C10: 159773 | D10: 113623 | E10: =C10-D10 -> 46150 | F10: =B10/C10 -> 0.24452192 | G10: =IFERROR(B10/E10,"") -> 0.84654388
A11: Devolved, local and church legislation | B11: 26150 | C11: 38099 | D11: 10319 | E11: =C11-D11 -> 27780 | F11: =B11/C11 -> 0.68636972 | G11: =IFERROR(B11/E11,"") -> 0.94132469
A12: ALL UK LEGISLATION | B12: =SUM(B7:B11) -> 143269 | C12: =SUM(C7:C11) -> 324622 | D12: =SUM(D7:D11) -> 139440 | E12: =C12-D12 -> 185182 | F12: =B12/C12 -> 0.44134101 | G12: =B12/E12 -> 0.77366591
A13: Instruments published, with text, that we do NOT hold — the recoverable work list | B13: =E12-B12 -> 41913 | G13: Already enumerated in scripts/ingest/v36/worklist.jsonl. Nothing needs discovering; it needs fetching.
A15: PART 2 — HOW MUCH OF THE REST DO WE KNOW ANYTHING ABOUT?
A16: Coverage state | B16: Sources | C16: Sections held | G16: What it means
A17: MEASURED | B17: =COUNTIF('Master Register'!$N$2:$N$126,A17) -> 7 | C17: =SUMIF('Master Register'!$N$2:$N$126,A17,'Master Register'!$L$2:$L$126) -> 1593298 | G17: A publisher walk exists. The percentage is a fact.
A18: CLAIMED | B18: =COUNTIF('Master Register'!$N$2:$N$126,A18) -> 5 | C18: =SUMIF('Master Register'!$N$2:$N$126,A18,'Master Register'!$L$2:$L$126) -> 81772 | G18: A target exists but its provenance is unproven. Treat as unmeasured until checked.
A19: UNMEASURED | B19: =COUNTIF('Master Register'!$N$2:$N$126,A19) -> 59 | C19: =SUMIF('Master Register'!$N$2:$N$126,A19,'Master Register'!$L$2:$L$126) -> 16568736 | G19: No denominator. No percentage is shown — and that blank is the honest answer.
A20: NOT STARTED | B20: =COUNTIF('Master Register'!$N$2:$N$126,A20) -> 42 | C20: =SUMIF('Master Register'!$N$2:$N$126,A20,'Master Register'!$L$2:$L$126) -> 0 | G20: Nothing held at all.
A21: BLOCKED | B21: =COUNTIF('Master Register'!$N$2:$N$126,A21) -> 1 | C21: =SUMIF('Master Register'!$N$2:$N$126,A21,'Master Register'!$L$2:$L$126) -> 0 | G21: Cannot be taken — licence-hostile.
A22: RETIRED | B22: =COUNTIF('Master Register'!$N$2:$N$126,A22) -> 3 | C22: =SUMIF('Master Register'!$N$2:$N$126,A22,'Master Register'!$L$2:$L$126) -> 28629 | G22: Superseded, but the rows were never deleted and are still served.
A23: LEGACY | B23: =COUNTIF('Master Register'!$N$2:$N$126,A23) -> 1 | C23: =SUMIF('Master Register'!$N$2:$N$126,A23,'Master Register'!$L$2:$L$126) -> 914274 | G23: Held in the old table; no search path reaches it.
A24: OUT OF SCOPE | B24: =COUNTIF('Master Register'!$N$2:$N$126,A24) -> 7 | C24: =SUMIF('Master Register'!$N$2:$N$126,A24,'Master Register'!$L$2:$L$126) -> 0 | G24: Private intellectual property. Cite by reference only.
A25: TOTAL (excluding the legacy table, which is not in corpus_sections) | B25: =SUM(B17:B24) -> 125 | C25: =SUM(C17:C24)-C23 -> 18272435
A27: PART 3 — BY TIER
A28: Tier | B28: Sources | C28: Sections held | D28: Of which NOT STARTED | E28: New proposals
A29: O Out of scope (private IP) | B29: =COUNTIF('Master Register'!$B$2:$B$126,A29) -> 7 | C29: =SUMIF('Master Register'!$B$2:$B$126,A29,'Master Register'!$L$2:$L$126) -> 0 | D29: =COUNTIFS('Master Register'!$B$2:$B$126,A29,'Master Register'!$E$2:$E$126,"NOT STARTED") -> 0 | E29: =COUNTIFS('Master Register'!$B$2:$B$126,A29,'Master Register'!$F$2:$F$126,"NEW") -> 0
A30: T1 The law itself | B30: =COUNTIF('Master Register'!$B$2:$B$126,A30) -> 15 | C30: =SUMIF('Master Register'!$B$2:$B$126,A30,'Master Register'!$L$2:$L$126) -> 2566613 | D30: =COUNTIFS('Master Register'!$B$2:$B$126,A30,'Master Register'!$E$2:$E$126,"NOT STARTED") -> 5 | E30: =COUNTIFS('Master Register'!$B$2:$B$126,A30,'Master Register'!$F$2:$F$126,"NEW") -> 1
A31: T2 Parliament (Westminster) | B31: =COUNTIF('Master Register'!$B$2:$B$126,A31) -> 30 | C31: =SUMIF('Master Register'!$B$2:$B$126,A31,'Master Register'!$L$2:$L$126) -> 14143412 | D31: =COUNTIFS('Master Register'!$B$2:$B$126,A31,'Master Register'!$E$2:$E$126,"NOT STARTED") -> 9 | E31: =COUNTIFS('Master Register'!$B$2:$B$126,A31,'Master Register'!$F$2:$F$126,"NEW") -> 8
A32: T3 Courts & tribunals | B32: =COUNTIF('Master Register'!$B$2:$B$126,A32) -> 12 | C32: =SUMIF('Master Register'!$B$2:$B$126,A32,'Master Register'!$L$2:$L$126) -> 405622 | D32: =COUNTIFS('Master Register'!$B$2:$B$126,A32,'Master Register'!$E$2:$E$126,"NOT STARTED") -> 6 | E32: =COUNTIFS('Master Register'!$B$2:$B$126,A32,'Master Register'!$F$2:$F$126,"NEW") -> 4
A33: T4 Devolved legislatures | B33: =COUNTIF('Master Register'!$B$2:$B$126,A33) -> 4 | C33: =SUMIF('Master Register'!$B$2:$B$126,A33,'Master Register'!$L$2:$L$126) -> 1431342 | D33: =COUNTIFS('Master Register'!$B$2:$B$126,A33,'Master Register'!$E$2:$E$126,"NOT STARTED") -> 1 | E33: =COUNTIFS('Master Register'!$B$2:$B$126,A33,'Master Register'!$F$2:$F$126,"NEW") -> 1
A34: T5 Government, regulators & guidance | B34: =COUNTIF('Master Register'!$B$2:$B$126,A34) -> 38 | C34: =SUMIF('Master Register'!$B$2:$B$126,A34,'Master Register'!$L$2:$L$126) -> 341112 | D34: =COUNTIFS('Master Register'!$B$2:$B$126,A34,'Master Register'!$E$2:$E$126,"NOT STARTED") -> 15 | E34: =COUNTIFS('Master Register'!$B$2:$B$126,A34,'Master Register'!$F$2:$F$126,"NEW") -> 12
A35: T6 EU & international | B35: =COUNTIF('Master Register'!$B$2:$B$126,A35) -> 12 | C35: =SUMIF('Master Register'!$B$2:$B$126,A35,'Master Register'!$L$2:$L$126) -> 269979 | D35: =COUNTIFS('Master Register'!$B$2:$B$126,A35,'Master Register'!$E$2:$E$126,"NOT STARTED") -> 2 | E35: =COUNTIFS('Master Register'!$B$2:$B$126,A35,'Master Register'!$F$2:$F$126,"NEW") -> 1
A36: T7 Local government | B36: =COUNTIF('Master Register'!$B$2:$B$126,A36) -> 4 | C36: =SUMIF('Master Register'!$B$2:$B$126,A36,'Master Register'!$L$2:$L$126) -> 0 | D36: =COUNTIFS('Master Register'!$B$2:$B$126,A36,'Master Register'!$E$2:$E$126,"NOT STARTED") -> 4 | E36: =COUNTIFS('Master Register'!$B$2:$B$126,A36,'Master Register'!$F$2:$F$126,"NEW") -> 4
A37: X Retired but still serving | B37: =COUNTIF('Master Register'!$B$2:$B$126,A37) -> 3 | C37: =SUMIF('Master Register'!$B$2:$B$126,A37,'Master Register'!$L$2:$L$126) -> 28629 | D37: =COUNTIFS('Master Register'!$B$2:$B$126,A37,'Master Register'!$E$2:$E$126,"NOT STARTED") -> 0 | E37: =COUNTIFS('Master Register'!$B$2:$B$126,A37,'Master Register'!$F$2:$F$126,"NEW") -> 0
A38: TOTAL (excluding the legacy table) | B38: =SUM(B29:B37) -> 125 | C38: =SUM(C29:C37)-914274 -> 18272435 | D38: =SUM(D29:D37) -> 42 | E38: =SUM(E29:E37) -> 31

Sheet Licences & Letters
A1: ID | B1: Source | C1: Corpus key(s) | D1: Licence code | E1: Licence status | F1: Commercial use OK? | G1: Verified | H1: What the licence actually says | I1: Risk to us — plain English | J1: CHARLIE ACTION — what to write | K1: Write to | L1: Urgency
A2: LIC01 | B2: Find Case Law (senior court judgments) | C2: tna-caselaw | D2: ojl-2.0 | E2: ACTION — WE ARE OUTSIDE THE LICENCE TODAY | F2: No — not without a further licence | G2: 12 Jun 2026 | H2: Open Justice Licence v2.0 permits reading and reproduction but EXPRESSLY EXCLUDES computational analysis — which the licence defines to include search indexing, bulk processing and machine learning. | I2: HIGH. We hold 74,896 judgments, have embedded them into a vector index and serve them through full-text search. That is computational analysis. This is not a future risk; it is the current state. | J2: Write to The National Archives applying for the separate computational-analysis licence. Explain: non-profit civic-technology platform, purpose is public legal understanding and legislative scrutiny, no redistribution of judgment text, attribution carried per section. | K2: caselawlicence@nationalarchives.gov.uk | L2: DO FIRST
A3: LIC02 | B3: BAILII — case law before 2001 | C3: bailii-pre-2001 (planned) | D3: BAILII terms | E3: ACTION — needed BEFORE the fetch | F3: Unknown | G3: not yet verified | H3: BAILII is a small charity. Its terms restrict systematic downloading and it has historically asked bulk users to make contact and contribute. | I3: HIGH if we start a 150,000+ judgment crawl unannounced. A blocked IP costs more than a week, and the reputational cost to a civic-tech project is worse. | J3: Write to BAILII BEFORE any bulk run: describe the project, the rate we propose (slow), offer attribution and a donation. Ask which databases we may and may not take. | K3: enquiries@bailii.org | L3: DO FIRST — gates the largest gap in the corpus
A4: LIC03 | B4: FCA Handbook | C4: fca-handbook | D4: fca-restricted | E4: ACTION — WE ARE OUTSIDE THE LICENCE TODAY | F4: No | G4: 12 Jun 2026 | H4: Reproduction, or storage in any retrieval system, requires the FCA's prior written permission. Reproducing the Handbook requires a licence agreement. | I4: HIGH. 3,661 sections are stored and indexed now. Any backfill toward the 150,000-section estimate multiplies the exposure. | J4: Write to the FCA requesting a Handbook licence for a non-commercial research and public-understanding platform. Ask explicitly whether indexing for search is covered. | K4: FCA — via fca.org.uk/contact, marked for the Handbook / legal team | L4: DO FIRST — gates a 146,000-section backfill
A5: LIC04 | B5: National Audit Office reports | C5: nao-reports | D5: nao-nc | E5: RESTRICTED — non-commercial only | F5: No | G5: 12 Jun 2026 | H5: Free re-use for non-commercial purposes with attribution. Commercial use requires express permission. | I5: MEDIUM. Fine for Scrutinise as a not-for-profit. Becomes a blocker the day a commercial arm launches. | J5: No action needed now. If a commercial arm is created, write to the NAO for permission. Flag the rows as commercial-excluded in the meantime. | K5: NAO — enquiries@nao.org.uk | L5: Before any commercial launch
A6: LIC05 | B6: ECtHR judgments (HUDOC) | C6: echr-hudoc | D6: echr-nc | E6: RESTRICTED — non-commercial only | F6: No | G6: 13 Jun 2026 | H6: Free reproduction with acknowledgment for private, information or education purposes. Commercial use requires prior written permission. | I6: MEDIUM. Same shape as the NAO position. | J6: No action now; write for commercial permission before any commercial launch. | K6: Council of Europe — publishing@echr.coe.int | L6: Before any commercial launch
A7: LIC06 | B7: OECD publications | C7: oecd | D7: cc-by-nc-4.0 (pre-Jul-2024) / cc-by-4.0 (post-Jul-2024) | E7: SPLIT — depends on publication date | F7: Partial | G7: V19 | H7: OECD content published before July 2024 is CC-BY-NC (non-commercial). Content published from July 2024 is CC-BY and freely usable including commercially. | I7: LOW, but the two vintages must be labelled separately or the whole collection has to be treated as non-commercial. | J7: No letter needed. Ask CC to date-split the 505 held rows and label them. | K7: — | L7: Housekeeping
A8: LIC07 | B8: IMF data | C8: (licence register entry) | D8: commercialUseExcluded=true | E8: RESTRICTED | F8: No | G8: recorded in register | H8: Commercial use excluded. The first such entry in the licence register. | I8: LOW while non-profit. | J8: None now. | K8: — | L8: Before any commercial launch
A9: LIC08 | B9: College of Policing APP | C9: college-of-policing | D9: pending-verification | E9: UNVERIFIED — cannot read the terms | F9: Unknown | G9: blocked | H9: The terms and conditions page is behind Cloudflare and cannot be read by our crawler. A footer grep is NOT verification — that rule is already in the playbook. | I9: MEDIUM. We hold 332 sections under an unknown licence and Charlie has asked for a large backfill of this source. | J9: Write to the College of Policing asking for the re-use terms for Authorised Professional Practice in writing. | K9: College of Policing — contactus@college.police.uk | L9: Before the APP backfill
A10: LIC09 | B10: Northern Ireland judgments | C10: ni-judgments | D10: pending-verification | E10: UNVERIFIED — Crown copyright asserted, no open licence stated | F10: Unknown | G10: 12 Jun 2026 | H10: The site asserts Crown copyright but states no open licence. Judgment sources are being treated cautiously given the Find Case Law precedent. | I10: MEDIUM. 7,772 judgments held. | J10: Write to the Judicial Studies Board / Lady Chief Justice's Office in Belfast asking for written re-use terms. | K10: Judiciary NI — via judiciaryni.uk contact form | L10: Within the census sprint
A11: LIC10 | B11: Tax tribunal decisions | C11: tax-tribunals | D11: pending-verification | E11: UNVERIFIED — no statement found | F11: Unknown | G11: 12 Jun 2026 | H11: No licence statement on the HMCTS legacy site. | I11: MEDIUM. 12,089 decisions held. | J11: Write to HMCTS asking for the re-use position on published tribunal decisions. | K11: HMCTS — via gov.uk contact | L11: Within the census sprint
A12: LIC11 | B12: Northern Ireland Law Commission | C12: nilawcom | D12: pending-verification | E12: UNVERIFIED — site SSL certificate dead | F12: Unknown | G12: — | H12: Cannot reach the site to read the terms. | I12: LOW — only 17 sections held. | J12: Write to the Department of Justice NI, which absorbed the Commission's functions, for the re-use position and an archive copy. | K12: DoJ NI — via justice-ni.gov.uk | L12: Low priority
... A21: LIC20 | B21: All gov.uk, legislation.gov.uk and parliamentary sources | C21: primary-acts-*, si-*, regional, retained-eu, hmrc-*, pwdata-*, committees-*, historic-hansard and others | D21: ogl-3.0 / opl-3.0 / eu-2011-833 | E21: CLEAR | F21: Yes | G21: 12 Jun 2026 | H21: Open Government Licence v3.0 and the Open Parliament Licence permit copying, publishing, adapting and commercial exploitation with attribution. | I21: NONE. This covers the large majority of the corpus by volume. | J21: None. Keep attribution carried per section. | K21: — | L21: Done
B23: THREE LETTERS TO WRITE FIRST — in this order
B24: 1. The National Archives (Find Case Law) — we are indexing 74,896 judgments under a licence that excludes computational analysis. This is the only one where we are outside the terms on content we already hold and serve.
B25: 2. The FCA — same problem, smaller volume (3,661 sections), but it also gates a 146,000-section backfill of the most commercially valuable corpus available to us.
B26: 3. BAILII — not a breach, but a courtesy that gates the single largest gap in the corpus. A charity that gets a polite letter first is an ally; one that finds a crawler is not.

Sheet Quangos
A1: Organisation | B1: GOV.UK slug | C1: Body type | D1: GOV.UK status | E1: Parent department | F1: Total docs on GOV.UK | G1: Relevant docs | H1: Guidance | I1: Statutory guidance | J1: Detailed guide | K1: Manual sections | L1: Manuals | M1: Policy papers | N1: Decisions | O1: Regulations | P1: Notices | Q1: Research | R1: Independent reports | S1: Impact assessments | T1: Corporate reports | U1: Consultation outcomes | V1: Government responses | W1: Other relevant | X1: Publishes on own site? | Y1: Ingest wave
A2: Air Accidents Investigation Branch | B2: air-accidents-investigation-branch | C2: Other | D2: live | E2: department-for-transport | F2: 12287 | G2: 11732 | H2: 21 | I2: 0 | J2: 1 | K2: 0 | L2: 0 | M2: 9 | N2: 0 | O2: 16 | P2: 0 | Q2: 0 | R2: 342 | S2: 0 | T2: 1 | U2: 0 | V2: 0 | W2: 11342 | X2: No | Y2: Wave 1 — GOV.UK Content API
A3: HM Revenue & Customs | B3: hm-revenue-customs | C3: Non-ministerial department | D3: live | F3: 100281 | G3: 8487 | H3: 1611 | I3: 76 | J3: 2047 | K3: 924 | L3: 66 | M3: 1905 | N3: 10 | O3: 0 | P3: 73 | Q3: 766 | R3: 4 | S3: 100 | T3: 454 | U3: 336 | V3: 23 | W3: 92 | X3: No | Y3: Wave 1 — GOV.UK Content API
A4: Environment Agency | B4: environment-agency | C4: Executive non-departmental public body | D4: live | E4: department-for-environment-food-rural-affairs | F4: 11443 | G4: 7639 | H4: 483 | I4: 186 | J4: 465 | K4: 184 | L4: 19 | M4: 421 | N4: 330 | O4: 0 | P4: 3981 | Q4: 1008 | R4: 3 | S4: 2 | T4: 134 | U4: 132 | V4: 11 | W4: 280 | X4: No | Y4: Wave 1 — GOV.UK Content API
A5: Department for Environment, Food & Rural Affairs | B5: department-for-environment-food-rural-affairs | C5: Ministerial department | D5: live | F5: 21049 | G5: 4630 | H5: 752 | I5: 132 | J5: 799 | K5: 9 | L5: 1 | M5: 1006 | N5: 181 | O5: 0 | P5: 21 | Q5: 528 | R5: 132 | S5: 15 | T5: 200 | U5: 504 | V5: 74 | W5: 276 | X5: No | Y5: Wave 1 — GOV.UK Content API
A6: Department for Education | B6: department-for-education | C6: Ministerial department | D6: live | F6: 11075 | G6: 4038 | H6: 1048 | I6: 82 | J6: 281 | K6: 165 | L6: 15 | M6: 322 | N6: 174 | O6: 0 | P6: 2 | Q6: 1233 | R6: 133 | S6: 93 | T6: 114 | U6: 301 | V6: 37 | W6: 38 | X6: No | Y6: Wave 1 — GOV.UK Content API
A7: Home Office | B7: home-office | C7: Ministerial department | D7: live | F7: 13921 | G7: 3943 | H7: 1277 | I7: 47 | J7: 123 | K7: 101 | L7: 1 | M7: 1162 | N7: 2 | O7: 0 | P7: 17 | Q7: 357 | R7: 194 | S7: 68 | T7: 305 | U7: 246 | V7: 11 | W7: 32 | X7: No | Y7: Wave 1 — GOV.UK Content API
A8: Department of Health and Social Care | B8: department-of-health-and-social-care | C8: Ministerial department | D8: live | F8: 10641 | G8: 3753 | H8: 1205 | I8: 69 | J8: 85 | K8: 34 | L8: 1 | M8: 1062 | N8: 5 | O8: 1 | P8: 9 | Q8: 210 | R8: 400 | S8: 101 | T8: 182 | U8: 280 | V8: 54 | W8: 55 | X8: No | Y8: Wave 1 — GOV.UK Content API
A9: Ministry of Defence | B9: ministry-of-defence | C9: Ministerial department | D9: live | F9: 14840 | G9: 3611 | H9: 1032 | I9: 3 | J9: 244 | K9: 0 | L9: 0 | M9: 288 | N9: 0 | O9: 608 | P9: 29 | Q9: 160 | R9: 82 | S9: 10 | T9: 538 | U9: 85 | V9: 7 | W9: 525 | X9: No | Y9: Wave 1 — GOV.UK Content API
A10: HM Treasury | B10: hm-treasury | C10: Ministerial department | D10: live | F10: 9657 | G10: 3359 | H10: 603 | I10: 19 | J10: 26 | K10: 0 | L10: 0 | M10: 1291 | N10: 0 | O10: 0 | P10: 15 | Q10: 146 | R10: 59 | S10: 9 | T10: 755 | U10: 359 | V10: 4 | W10: 73 | X10: No | Y10: Wave 1 — GOV.UK Content API
A11: Foreign, Commonwealth & Development Office | B11: foreign-commonwealth-development-office | C11: Ministerial department | D11: live | F11: 48187 | G11: 3189 | H11: 1505 | I11: 39 | J11: 508 | K11: 0 | L11: 0 | M11: 769 | N11: 9 | O11: 0 | P11: 8 | Q11: 91 | R11: 9 | S11: 10 | T11: 167 | U11: 0 | V11: 71 | W11: 3 | X11: No | Y11: Wave 1 — GOV.UK Content API
A12: Department for Transport | B12: department-for-transport | C12: Ministerial department | D12: live | F12: 10528 | G12: 3078 | H12: 709 | I12: 52 | J12: 109 | K12: 62 | L12: 2 | M12: 368 | N12: 142 | O12: 0 | P12: 41 | Q12: 678 | R12: 114 | S12: 19 | T12: 274 | U12: 446 | V12: 21 | W12: 41 | X12: No | Y12: Wave 1 — GOV.UK Content API
A13: Department for Work and Pensions | B13: department-for-work-pensions | C13: Ministerial department | D13: live | F13: 10821 | G13: 2847 | H13: 518 | I13: 13 | J13: 115 | K13: 28 | L13: 1 | M13: 318 | N13: 2 | O13: 0 | P13: 1 | Q13: 887 | R13: 180 | S13: 181 | T13: 320 | U13: 246 | V13: 14 | W13: 23 | X13: No | Y13: Wave 1 — GOV.UK Content API
A14: Department for Energy Security and Net Zero | B14: department-for-energy-security-and-net-zero | C14: Ministerial department | D14: live | F14: 4839 | G14: 2766 | H14: 392 | I14: 13 | J14: 96 | K14: 9 | L14: 1 | M14: 243 | N14: 683 | O14: 0 | P14: 407 | Q14: 645 | R14: 34 | S14: 10 | T14: 56 | U14: 128 | V14: 1 | W14: 48 | X14: No | Y14: Wave 1 — GOV.UK Content API
A15: Cabinet Office | B15: cabinet-office | C15: Ministerial department | D15: live | F15: 7668 | G15: 2758 | H15: 845 | I15: 6 | J15: 109 | K15: 0 | L15: 0 | M15: 1012 | N15: 57 | O15: 0 | P15: 27 | Q15: 135 | R15: 80 | S15: 13 | T15: 357 | U15: 77 | V15: 20 | W15: 20 | X15: No | Y15: Wave 1 — GOV.UK Content API
A16: HM Courts & Tribunals Service | B16: hm-courts-and-tribunals-service | C16: Executive agency | D16: live | E16: ministry-of-justice | F16: 156942 | G16: 2534 | H16: 181 | I16: 1 | J16: 126 | K16: 0 | L16: 0 | M16: 7 | N16: 1 | O16: 0 | P16: 1 | Q16: 19 | R16: 2 | S16: 0 | T16: 52 | U16: 12 | V16: 12 | W16: 2120 | X16: No | Y16: Wave 1 — GOV.UK Content API
A17: Ministry of Justice | B17: ministry-of-justice | C17: Ministerial department | D17: live | F17: 8026 | G17: 2509 | H17: 470 | I17: 9 | J17: 480 | K17: 12 | L17: 2 | M17: 582 | N17: 1 | O17: 0 | P17: 9 | Q17: 343 | R17: 65 | S17: 15 | T17: 300 | U17: 175 | V17: 8 | W17: 38 | X17: No | Y17: Wave 1 — GOV.UK Content API
A18: Ministry of Housing, Communities & Local Government (2018 to 2021) | B18: ministry-of-housing-communities-and-local-government-2018-2021 | C18: Ministerial department | D18: closed | F18: 10849 | G18: 2504 | H18: 698 | I18: 35 | J18: 120 | K18: 0 | L18: 0 | M18: 635 | N18: 5 | O18: 0 | P18: 2 | Q18: 228 | R18: 91 | S18: 106 | T18: 94 | U18: 372 | V18: 88 | W18: 30 | X18: No | Y18: Wave 3 — archive only
A19: Public Health England | B19: public-health-england | C19: Executive agency | D19: closed | E19: department-of-health-and-social-care | F19: 5598 | G19: 2457 | H19: 996 | I19: 0 | J19: 159 | K19: 0 | L19: 0 | M19: 50 | N19: 0 | O19: 0 | P19: 0 | Q19: 1018 | R19: 53 | S19: 5 | T19: 131 | U19: 33 | V19: 0 | W19: 12 | X19: No | Y19: Wave 3 — archive only
A20: Department for Business, Energy & Industrial Strategy | B20: department-for-business-energy-and-industrial-strategy | C20: Ministerial department | D20: closed | F20: 7019 | G20: 2399 | H20: 379 | I20: 8 | J20: 129 | K20: 0 | L20: 0 | M20: 259 | N20: 171 | O20: 1 | P20: 233 | Q20: 609 | R20: 65 | S20: 11 | T20: 177 | U20: 320 | V20: 16 | W20: 21 | X20: No | Y20: Wave 3 — archive only
A21: Company Names Tribunal | B21: company-names-tribunal | C21: Other | D21: live | E21: intellectual-property-office | F21: 2315 | G21: 2302 | H21: 6 | I21: 0 | J21: 1 | K21: 0 | L21: 0 | M21: 0 | N21: 2287 | O21: 0 | P21: 8 | Q21: 0 | R21: 0 | S21: 0 | T21: 0 | U21: 0 | V21: 0 | W21: 0 | X21: No | Y21: Wave 1 — GOV.UK Content API
A22: Office of the Schools Adjudicator | B22: office-of-the-schools-adjudicator | C22: Other | D22: live | E22: department-for-education | F22: 2230 | G22: 2217 | H22: 0 | I22: 0 | J22: 3 | K22: 0 | L22: 0 | M22: 0 | N22: 2213 | O22: 0 | P22: 0 | Q22: 0 | R22: 0 | S22: 0 | T22: 1 | U22: 0 | V22: 0 | W22: 0 | X22: No | Y22: Wave 1 — GOV.UK Content API
A23: Foreign & Commonwealth Office | B23: foreign-commonwealth-office | C23: Ministerial department | D23: closed | F23: 16523 | G23: 2204 | H23: 816 | I23: 0 | J23: 68 | K23: 0 | L23: 0 | M23: 406 | N23: 0 | O23: 0 | P23: 8 | Q23: 442 | R23: 20 | S23: 5 | T23: 390 | U23: 20 | V23: 27 | W23: 2 | X23: No | Y23: Wave 3 — archive only
A24: Department for International Development | B24: department-for-international-development | C24: Ministerial department | D24: closed | F24: 5621 | G24: 2073 | H24: 167 | I24: 0 | J24: 46 | K24: 0 | L24: 0 | M24: 737 | N24: 0 | O24: 0 | P24: 2 | Q24: 93 | R24: 596 | S24: 19 | T24: 373 | U24: 6 | V24: 33 | W24: 1 | X24: No | Y24: Wave 3 — archive only
A25: Department for Digital, Culture, Media & Sport | B25: department-for-digital-culture-media-sport | C25: Ministerial department | D25: closed | F25: 7420 | G25: 2068 | H25: 301 | I25: 7 | J25: 139 | K25: 0 | L25: 0 | M25: 411 | N25: 9 | O25: 4 | P25: 36 | Q25: 290 | R25: 93 | S25: 30 | T25: 517 | U25: 181 | V25: 12 | W25: 38 | X25: No | Y25: Wave 3 — archive only
A26: Department for Business and Trade | B26: department-for-business-and-trade | C26: Ministerial department | D26: live | F26: 4133 | G26: 2031 | H26: 588 | I26: 29 | J26: 301 | K26: 16 | L26: 2 | M26: 335 | N26: 40 | O26: 0 | P26: 219 | Q26: 281 | R26: 49 | S26: 16 | T26: 53 | U26: 53 | V26: 5 | W26: 44 | X26: No | Y26: Wave 1 — GOV.UK Content API
A27: Upper Tribunal (Administrative Appeals Chamber) | B27: upper-tribunal-administrative-appeals-chamber | C27: Tribunal | D27: live | E27: hm-courts-and-tribunals-service | F27: 2022 | G27: 2019 | H27: 0 | I27: 0 | J27: 0 | K27: 0 | L27: 0 | M27: 0 | N27: 0 | O27: 0 | P27: 0 | Q27: 0 | R27: 0 | S27: 0 | T27: 0 | U27: 0 | V27: 0 | W27: 2019 | X27: No | Y27: Wave 1 — GOV.UK Content API
A28: Ministry of Housing, Communities and Local Government | B28: ministry-of-housing-communities-local-government | C28: Ministerial department | D28: live | F28: 3254 | G28: 1753 | H28: 709 | I28: 50 | J28: 411 | K28: 110 | L28: 10 | M28: 120 | N28: 10 | O28: 0 | P28: 2 | Q28: 162 | R28: 49 | S28: 4 | T28: 12 | U28: 55 | V28: 0 | W28: 49 | X28: No | Y28: Wave 1 — GOV.UK Content API
A29: Intellectual Property Office | B29: intellectual-property-office | C29: Executive agency | D29: live | E29: department-for-science-innovation-and-technology | F29: 2754 | G29: 1742 | H29: 158 | I29: 78 | J29: 130 | K29: 434 | L29: 7 | M29: 9 | N29: 441 | O29: 0 | P29: 135 | Q29: 145 | R29: 0 | S29: 1 | T29: 23 | U29: 44 | V29: 0 | W29: 137 | X29: No | Y29: Wave 1 — GOV.UK Content API
A30: Department for Business, Innovation & Skills | B30: department-for-business-innovation-skills | C30: Ministerial department | D30: closed | F30: 6029 | G30: 1666 | H30: 19 | I30: 0 | J30: 4 | K30: 0 | L30: 0 | M30: 415 | N30: 2 | O30: 0 | P30: 8 | Q30: 719 | R30: 57 | S30: 92 | T30: 135 | U30: 188 | V30: 8 | W30: 19 | X30: No | Y30: Wave 3 — archive only
A31: Teaching Regulation Agency | B31: teaching-regulation-agency | C31: Executive agency | D31: live | E31: department-for-education | F31: 1672 | G31: 1663 | H31: 8 | I31: 0 | J31: 6 | K31: 0 | L31: 0 | M31: 0 | N31: 1639 | O31: 0 | P31: 0 | Q31: 0 | R31: 0 | S31: 0 | T31: 10 | U31: 0 | V31: 0 | W31: 0 | X31: No | Y31: Wave 1 — GOV.UK Content API
A32: Certification Officer | B32: certification-officer | C32: Other | D32: live | E32: department-for-business-and-trade | F32: 1795 | G32: 1587 | H32: 6 | I32: 0 | J32: 11 | K32: 0 | L32: 0 | M32: 0 | N32: 525 | O32: 0 | P32: 0 | Q32: 0 | R32: 0 | S32: 0 | T32: 1045 | U32: 0 | V32: 0 | W32: 0 | X32: No | Y32: Wave 1 — GOV.UK Content API
A33: UK Health Security Agency | B33: uk-health-security-agency | C33: Executive agency | D33: live | E33: department-of-health-and-social-care | F33: 3564 | G33: 1573 | H33: 698 | I33: 0 | J33: 375 | K33: 0 | L33: 0 | M33: 5 | N33: 0 | O33: 0 | P33: 0 | Q33: 426 | R33: 9 | S33: 1 | T33: 54 | U33: 2 | V33: 0 | W33: 3 | X33: No | Y33: Wave 1 — GOV.UK Content API
A34: Department of Energy & Climate Change | B34: department-of-energy-climate-change | C34: Ministerial department | D34: closed | F34: 5098 | G34: 1466 | H34: 142 | I34: 2 | J34: 2 | K34: 0 | L34: 0 | M34: 398 | N34: 2 | O34: 3 | P34: 1 | Q34: 323 | R34: 50 | S34: 49 | T34: 213 | U34: 234 | V34: 24 | W34: 23 | X34: No | Y34: Wave 3 — archive only
A35: UK Visas and Immigration | B35: uk-visas-and-immigration | C35: Sub organisation | D35: live | E35: home-office | F35: 2574 | G35: 1416 | H35: 955 | I35: 4 | J35: 50 | K35: 0 | L35: 0 | M35: 321 | N35: 0 | O35: 0 | P35: 1 | Q35: 32 | R35: 6 | S35: 20 | T35: 12 | U35: 10 | V35: 0 | W35: 5 | X35: No | Y35: Wave 1 — GOV.UK Content API
A36: High Speed Two (HS2) Limited | B36: high-speed-two-limited | C36: Executive non-departmental public body | D36: live | E36: department-for-transport | F36: 2437 | G36: 1380 | H36: 141 | I36: 3 | J36: 2 | K36: 0 | L36: 0 | M36: 211 | N36: 2 | O36: 0 | P36: 3 | Q36: 64 | R36: 81 | S36: 759 | T36: 68 | U36: 46 | V36: 0 | W36: 0 | X36: No | Y36: Wave 1 — GOV.UK Content API
A37: Department for Levelling Up, Housing and Communities | B37: department-for-levelling-up-housing-and-communities | C37: Other | D37: closed | F37: 3321 | G37: 1324 | H37: 408 | I37: 29 | J37: 363 | K37: 0 | L37: 0 | M37: 208 | N37: 4 | O37: 0 | P37: 1 | Q37: 128 | R37: 65 | S37: 6 | T37: 11 | U37: 80 | V37: 0 | W37: 21 | X37: No | Y37: Wave 3 — archive only
A38: Marine Accident Investigation Branch | B38: marine-accident-investigation-branch | C38: Other | D38: live | E38: department-for-transport | F38: 1695 | G38: 1320 | H38: 12 | I38: 0 | J38: 0 | K38: 0 | L38: 0 | M38: 8 | N38: 0 | O38: 0 | P38: 0 | Q38: 175 | R38: 0 | S38: 0 | T38: 26 | U38: 3 | V38: 0 | W38: 1096 | X38: No | Y38: Wave 1 — GOV.UK Content API
A39: Department for Culture, Media and Sport | B39: department-for-culture-media-and-sport | C39: Ministerial department | D39: live | F39: 2477 | G39: 1316 | H39: 229 | I39: 9 | J39: 155 | K39: 0 | L39: 0 | M39: 317 | N39: 0 | O39: 1 | P39: 37 | Q39: 352 | R39: 76 | S39: 23 | T39: 76 | U39: 27 | V39: 0 | W39: 14 | X39: No | Y39: Wave 1 — GOV.UK Content API
A40: Department for Science, Innovation and Technology | B40: department-for-science-innovation-and-technology | C40: Ministerial department | D40: live | F40: 2718 | G40: 1306 | H40: 217 | I40: 5 | J40: 144 | K40: 5 | L40: 1 | M40: 300 | N40: 0 | O40: 3 | P40: 119 | Q40: 349 | R40: 78 | S40: 12 | T40: 42 | U40: 13 | V40: 4 | W40: 14 | X40: No | Y40: Wave 1 — GOV.UK Content API
A41: Rural Payments Agency | B41: rural-payments-agency | C41: Executive agency | D41: live | E41: department-for-environment-food-rural-affairs | F41: 3444 | G41: 1256 | H41: 918 | I41: 4 | J41: 135 | K41: 100 | L41: 9 | M41: 8 | N41: 0 | O41: 0 | P41: 45 | Q41: 2 | R41: 0 | S41: 0 | T41: 33 | U41: 2 | V41: 0 | W41: 0 | X41: No | Y41: Wave 1 — GOV.UK Content API
A42: Maritime and Coastguard Agency | B42: maritime-and-coastguard-agency | C42: Executive agency | D42: live | E42: department-for-transport | F42: 1955 | G42: 1220 | H42: 825 | I42: 43 | J42: 91 | K42: 11 | L42: 2 | M42: 8 | N42: 0 | O42: 0 | P42: 3 | Q42: 26 | R42: 7 | S42: 2 | T42: 47 | U42: 130 | V42: 0 | W42: 25 | X42: No | Y42: Wave 1 — GOV.UK Content API
A43: Natural England | B43: natural-england | C43: Executive non-departmental public body | D43: live | E43: department-for-environment-food-rural-affairs | F43: 2581 | G43: 1189 | H43: 239 | I43: 58 | J43: 141 | K43: 0 | L43: 0 | M43: 32 | N43: 52 | O43: 0 | P43: 144 | Q43: 11 | R43: 0 | S43: 1 | T43: 106 | U43: 363 | V43: 1 | W43: 41 | X43: No | Y43: Wave 1 — GOV.UK Content API
A44: Traffic Commissioners for Great Britain | B44: traffic-commissioners | C44: Tribunal | D44: live | E44: department-for-transport | F44: 1386 | G44: 1105 | H44: 19 | I44: 16 | J44: 35 | K44: 0 | L44: 0 | M44: 2 | N44: 837 | O44: 0 | P44: 0 | Q44: 0 | R44: 2 | S44: 0 | T44: 15 | U44: 14 | V44: 0 | W44: 165 | X44: No | Y44: Wave 1 — GOV.UK Content API
A45: Ofqual | B45: ofqual | C45: Non-ministerial department | D45: live | E45: department-for-education | F45: 2068 | G45: 1059 | H45: 182 | I45: 79 | J45: 22 | K45: 43 | L45: 4 | M45: 2 | N45: 40 | O45: 148 | P45: 100 | Q45: 221 | R45: 2 | S45: 0 | T45: 62 | U45: 150 | V45: 0 | W45: 4 | X45: No | Y45: Wave 1 — GOV.UK Content API
A46: HM Prison and Probation Service | B46: hm-prison-and-probation-service | C46: Executive agency | D46: live | E46: ministry-of-justice | F46: 1571 | G46: 1016 | H46: 235 | I46: 0 | J46: 440 | K46: 0 | L46: 0 | M46: 221 | N46: 0 | O46: 0 | P46: 1 | Q46: 24 | R46: 14 | S46: 0 | T46: 76 | U46: 5 | V46: 0 | W46: 0 | X46: No | Y46: Wave 1 — GOV.UK Content API
A47: Scientific Advisory Group for Emergencies | B47: scientific-advisory-group-for-emergencies | C47: Other | D47: live | F47: 1158 | G47: 1010 | H47: 3 | I47: 0 | J47: 0 | K47: 0 | L47: 0 | M47: 2 | N47: 0 | O47: 0 | P47: 0 | Q47: 1003 | R47: 1 | S47: 0 | T47: 1 | U47: 0 | V47: 0 | W47: 0 | X47: No | Y47: Wave 1 — GOV.UK Content API
A48: Central Arbitration Committee | B48: central-arbitration-committee | C48: Tribunal | D48: live | E48: department-for-business-and-trade | F48: 1019 | G48: 964 | H48: 5 | I48: 0 | J48: 27 | K48: 0 | L48: 0 | M48: 0 | N48: 929 | O48: 0 | P48: 1 | Q48: 0 | R48: 0 | S48: 0 | T48: 2 | U48: 0 | V48: 0 | W48: 0 | X48: No | Y48: Wave 1 — GOV.UK Content API
A49: Medicines and Healthcare products Regulatory Agency | B49: medicines-and-healthcare-products-regulatory-agency | C49: Executive agency | D49: live | E49: department-of-health-and-social-care | F49: 4464 | G49: 943 | H49: 233 | I49: 1 | J49: 158 | K49: 0 | L49: 0 | M49: 7 | N49: 346 | O49: 1 | P49: 4 | Q49: 42 | R49: 4 | S49: 0 | T49: 58 | U49: 51 | V49: 7 | W49: 31 | X49: No | Y49: Wave 1 — GOV.UK Content API
A50: Competition and Markets Authority | B50: competition-and-markets-authority | C50: Non-ministerial department | D50: live | E50: department-for-business-and-trade | F50: 6314 | G50: 916 | H50: 305 | I50: 0 | J50: 28 | K50: 0 | L50: 0 | M50: 39 | N50: 6 | O50: 0 | P50: 12 | Q50: 108 | R50: 31 | S50: 11 | T50: 174 | U50: 193 | V50: 2 | W50: 7 | X50: No | Y50: Wave 1 — GOV.UK Content API
A51: Government Digital Service | B51: government-digital-service | C51: Sub organisation | D51: live | E51: department-for-science-innovation-and-technology | F51: 1408 | G51: 819 | H51: 100 | I51: 0 | J51: 176 | K51: 0 | L51: 0 | M51: 25 | N51: 0 | O51: 0 | P51: 1 | Q51: 12 | R51: 5 | S51: 0 | T51: 9 | U51: 4 | V51: 0 | W51: 487 | X51: No | Y51: Wave 1 — GOV.UK Content API
A52: Regulatory Policy Committee | B52: regulatory-policy-committee | C52: Advisory non-departmental public body | D52: live | E52: department-for-business-and-trade | F52: 816 | G52: 797 | H52: 19 | I52: 0 | J52: 0 | K52: 0 | L52: 0 | M52: 0 | N52: 0 | O52: 0 | P52: 0 | Q52: 776 | R52: 1 | S52: 0 | T52: 1 | U52: 0 | V52: 0 | W52: 0 | X52: No | Y52: Wave 1 — GOV.UK Content API
A53: Rail Accident Investigation Branch | B53: rail-accident-investigation-branch | C53: Other | D53: live | E53: department-for-transport | F53: 1068 | G53: 791 | H53: 11 | I53: 0 | J53: 1 | K53: 0 | L53: 0 | M53: 10 | N53: 0 | O53: 0 | P53: 0 | Q53: 28 | R53: 122 | S53: 0 | T53: 23 | U53: 0 | V53: 0 | W53: 596 | X53: No | Y53: Wave 1 — GOV.UK Content API
A54: Department for International Trade | B54: department-for-international-trade | C54: Other | D54: closed | F54: 2795 | G54: 759 | H54: 202 | I54: 2 | J54: 118 | K54: 0 | L54: 0 | M54: 108 | N54: 19 | O54: 0 | P54: 139 | Q54: 111 | R54: 3 | S54: 13 | T54: 20 | U54: 18 | V54: 5 | W54: 1 | X54: No | Y54: Wave 3 — archive only
A55: Marine Management Organisation | B55: marine-management-organisation | C55: Executive non-departmental public body | D55: live | E55: department-for-environment-food-rural-affairs | F55: 2049 | G55: 736 | H55: 104 | I55: 64 | J55: 130 | K55: 0 | L55: 0 | M55: 19 | N55: 59 | O55: 0 | P55: 12 | Q55: 175 | R55: 0 | S55: 2 | T55: 28 | U55: 39 | V55: 11 | W55: 93 | X55: No | Y55: Wave 1 — GOV.UK Content API
A56: Ofsted | B56: ofsted | C56: Non-ministerial department | D56: live | E56: department-for-education | F56: 1996 | G56: 695 | H56: 116 | I56: 0 | J56: 92 | K56: 13 | L56: 1 | M56: 6 | N56: 0 | O56: 0 | P56: 0 | Q56: 306 | R56: 5 | S56: 2 | T56: 100 | U56: 48 | V56: 4 | W56: 2 | X56: No | Y56: Wave 1 — GOV.UK Content API
A57: Military Aviation Authority | B57: military-aviation-authority | C57: Sub organisation | D57: live | E57: ministry-of-defence | F57: 753 | G57: 687 | H57: 62 | I57: 0 | J57: 0 | K57: 0 | L57: 0 | M57: 0 | N57: 0 | O57: 603 | P57: 0 | Q57: 1 | R57: 2 | S57: 0 | T57: 19 | U57: 0 | V57: 0 | W57: 0 | X57: No | Y57: Wave 1 — GOV.UK Content API
A58: Driver and Vehicle Standards Agency | B58: driver-and-vehicle-standards-agency | C58: Executive agency | D58: live | E58: department-for-transport | F58: 1303 | G58: 652 | H58: 239 | I58: 5 | J58: 112 | K58: 138 | L58: 13 | M58: 6 | N58: 0 | O58: 0 | P58: 0 | Q58: 45 | R58: 1 | S58: 25 | T58: 40 | U58: 24 | V58: 1 | W58: 3 | X58: No | Y58: Wave 1 — GOV.UK Content API
A59: Regulator of Social Housing | B59: regulator-of-social-housing | C59: Executive non-departmental public body | D59: live | E59: ministry-of-housing-communities-local-government | F59: 1162 | G59: 645 | H59: 42 | I59: 0 | J59: 68 | K59: 0 | L59: 0 | M59: 6 | N59: 344 | O59: 0 | P59: 4 | Q59: 140 | R59: 0 | S59: 1 | T59: 15 | U59: 12 | V59: 0 | W59: 13 | X59: No | Y59: Wave 1 — GOV.UK Content API
A60: Animal and Plant Health Agency | B60: animal-and-plant-health-agency | C60: Executive agency | D60: live | E60: department-for-environment-food-rural-affairs | F60: 3722 | G60: 643 | H60: 207 | I60: 20 | J60: 246 | K60: 0 | L60: 0 | M60: 18 | N60: 0 | O60: 0 | P60: 0 | Q60: 113 | R60: 0 | S60: 0 | T60: 36 | U60: 3 | V60: 0 | W60: 0 | X60: No | Y60: Wave 1 — GOV.UK Content API
A61: Valuation Office Agency | B61: valuation-office-agency | C61: Executive agency | D61: closed | E61: hm-revenue-customs | F61: 1315 | G61: 612 | H61: 51 | I61: 0 | J61: 43 | K61: 0 | L61: 0 | M61: 3 | N61: 361 | O61: 0 | P61: 0 | Q61: 116 | R61: 0 | S61: 0 | T61: 35 | U61: 3 | V61: 0 | W61: 0 | X61: No | Y61: Wave 3 — archive only
A62: Advisory Committee on Business Appointments | B62: advisory-committee-on-business-appointments | C62: Advisory non-departmental public body | D62: live | E62: cabinet-office | F62: 713 | G62: 586 | H62: 1 | I62: 0 | J62: 0 | K62: 0 | L62: 0 | M62: 0 | N62: 571 | O62: 0 | P62: 0 | Q62: 0 | R62: 0 | S62: 0 | T62: 14 | U62: 0 | V62: 0 | W62: 0 | X62: No | Y62: Wave 1 — GOV.UK Content API
A63: Government Office for Science | B63: government-office-for-science | C63: Other | D63: live | E63: department-for-science-innovation-and-technology | F63: 805 | G63: 537 | H63: 57 | I63: 0 | J63: 2 | K63: 0 | L63: 0 | M63: 2 | N63: 0 | O63: 0 | P63: 10 | Q63: 429 | R63: 1 | S63: 19 | T63: 14 | U63: 2 | V63: 1 | W63: 0 | X63: No | Y63: Wave 1 — GOV.UK Content API
A64: NHS England | B64: nhs-england | C64: Executive non-departmental public body | D64: exempt | E64: department-of-health-and-social-care | F64: 3588 | G64: 503 | H64: 360 | I64: 6 | J64: 33 | K64: 0 | L64: 0 | M64: 22 | N64: 0 | O64: 0 | P64: 0 | Q64: 32 | R64: 1 | S64: 1 | T64: 35 | U64: 8 | V64: 0 | W64: 5 | X64: YES — off GOV.UK | Y64: Wave 2 — own-site crawl, not scoped
A65: The Charity Commission | B65: charity-commission | C65: Non-ministerial department | D65: live | E65: department-for-culture-media-and-sport | F65: 1087 | G65: 460 | H65: 94 | I65: 5 | J65: 82 | K65: 0 | L65: 0 | M65: 55 | N65: 76 | O65: 0 | P65: 0 | Q65: 57 | R65: 1 | S65: 1 | T65: 70 | U65: 9 | V65: 10 | W65: 0 | X65: No | Y65: Wave 1 — GOV.UK Content API
A66: The Insolvency Service | B66: insolvency-service | C66: Executive agency | D66: live | E66: department-for-business-and-trade | F66: 1617 | G66: 448 | H66: 75 | I66: 2 | J66: 95 | K66: 92 | L66: 2 | M66: 2 | N66: 13 | O66: 2 | P66: 2 | Q66: 18 | R66: 1 | S66: 0 | T66: 127 | U66: 13 | V66: 1 | W66: 3 | X66: No | Y66: Wave 1 — GOV.UK Content API
... A76: Office for Product Safety and Standards | B76: office-for-product-safety-and-standards | C76: Sub organisation | D76: live | E76: department-for-business-and-trade | F76: 3982 | G76: 319 | H76: 79 | I76: 26 | J76: 107 | K76: 0 | L76: 0 | M76: 11 | N76: 0 | O76: 1 | P76: 0 | Q76: 75 | R76: 4 | S76: 0 | T76: 8 | U76: 5 | V76: 0 | W76: 3 | X76: No | Y76: Wave 1 — GOV.UK Content API
A77: Northern Ireland Office | B77: northern-ireland-office | C77: Ministerial department | D77: live | F77: 2298 | G77: 314 | H77: 21 | I77: 6 | J77: 4 | K77: 0 | L77: 0 | M77: 75 | N77: 1 | O77: 0 | P77: 2 | Q77: 3 | R77: 19 | S77: 0 | T77: 140 | U77: 14 | V77: 16 | W77: 13 | X77: No | Y77: Wave 1 — GOV.UK Content API
A78: Nuclear Decommissioning Authority | B78: nuclear-decommissioning-authority | C78: Executive non-departmental public body | D78: live | E78: department-for-energy-security-and-net-zero | F78: 994 | G78: 308 | H78: 17 | I78: 0 | J78: 4 | K78: 0 | L78: 0 | M78: 4 | N78: 0 | O78: 0 | P78: 4 | Q78: 6 | R78: 3 | S78: 5 | T78: 245 | U78: 19 | V78: 0 | W78: 1 | X78: No | Y78: Wave 1 — GOV.UK Content API
A79: Government Equalities Office | B79: government-equalities-office | C79: Other | D79: closed | E79: cabinet-office | F79: 789 | G79: 294 | H79: 64 | I79: 1 | J79: 3 | K79: 0 | L79: 0 | M79: 60 | N79: 0 | O79: 0 | P79: 0 | Q79: 77 | R79: 31 | S79: 15 | T79: 24 | U79: 15 | V79: 1 | W79: 3 | X79: No | Y79: Wave 3 — archive only
A80: Office for Health Improvement and Disparities | B80: office-for-health-improvement-and-disparities | C80: Sub organisation | D80: live | E80: department-of-health-and-social-care | F80: 1006 | G80: 277 | H80: 93 | I80: 0 | J80: 99 | K80: 0 | L80: 0 | M80: 2 | N80: 0 | O80: 0 | P80: 0 | Q80: 53 | R80: 20 | S80: 0 | T80: 3 | U80: 5 | V80: 0 | W80: 2 | X80: No | Y80: Wave 1 — GOV.UK Content API
A81: Monitor | B81: monitor | C81: Executive non-departmental public body | D81: closed | E81: department-of-health-and-social-care | F81: 1007 | G81: 269 | H81: 69 | I81: 24 | J81: 18 | K81: 0 | L81: 0 | M81: 6 | N81: 4 | O81: 0 | P81: 5 | Q81: 43 | R81: 21 | S81: 1 | T81: 44 | U81: 24 | V81: 0 | W81: 10 | X81: No | Y81: Wave 3 — archive only
A82: UK Export Finance | B82: uk-export-finance | C82: Ministerial department | D82: live | F82: 1405 | G82: 268 | H82: 26 | I82: 0 | J82: 31 | K82: 0 | L82: 0 | M82: 10 | N82: 0 | O82: 0 | P82: 114 | Q82: 7 | R82: 1 | S82: 1 | T82: 72 | U82: 6 | V82: 0 | W82: 0 | X82: No | Y82: Wave 1 — GOV.UK Content API
A83: Independent Chief Inspector of Borders and Immigration | B83: independent-chief-inspector-of-borders-and-immigration | C83: Independent monitoring body | D83: live | E83: home-office | F83: 521 | G83: 261 | H83: 5 | I83: 0 | J83: 0 | K83: 0 | L83: 0 | M83: 1 | N83: 0 | O83: 0 | P83: 0 | Q83: 1 | R83: 227 | S83: 0 | T83: 27 | U83: 0 | V83: 0 | W83: 0 | X83: No | Y83: Wave 1 — GOV.UK Content API
A84: Veterinary Medicines Directorate | B84: veterinary-medicines-directorate | C84: Executive agency | D84: live | E84: department-for-environment-food-rural-affairs | F84: 872 | G84: 260 | H84: 19 | I84: 0 | J84: 106 | K84: 34 | L84: 4 | M84: 8 | N84: 0 | O84: 0 | P84: 35 | Q84: 27 | R84: 0 | S84: 0 | T84: 22 | U84: 3 | V84: 0 | W84: 2 | X84: No | Y84: Wave 1 — GOV.UK Content API
A85: Government Actuary's Department | B85: government-actuarys-department | C85: Non-ministerial department | D85: live | E85: hm-treasury | F85: 704 | G85: 254 | H85: 91 | I85: 0 | J85: 5 | K85: 0 | L85: 0 | M85: 2 | N85: 0 | O85: 1 | P85: 0 | Q85: 81 | R85: 25 | S85: 0 | T85: 46 | U85: 3 | V85: 0 | W85: 0 | X85: No | Y85: Wave 1 — GOV.UK Content API
A86: UK Hydrographic Office | B86: uk-hydrographic-office | C86: Executive agency | D86: live | E86: ministry-of-defence | F86: 428 | G86: 254 | H86: 21 | I86: 0 | J86: 10 | K86: 0 | L86: 0 | M86: 3 | N86: 0 | O86: 1 | P86: 0 | Q86: 190 | R86: 0 | S86: 0 | T86: 29 | U86: 0 | V86: 0 | W86: 0 | X86: No | Y86: Wave 1 — GOV.UK Content API
A87: Welsh Government | B87: welsh-government | C87: Devolved government | D87: exempt | F87: 1784 | G87: 251 | H87: 8 | I87: 77 | J87: 21 | K87: 0 | L87: 0 | M87: 69 | N87: 1 | O87: 0 | P87: 1 | Q87: 9 | R87: 3 | S87: 0 | T87: 9 | U87: 42 | V87: 1 | W87: 10 | X87: YES — off GOV.UK | Y87: Wave 2 — own-site crawl, not scoped
A88: Nuclear Waste Services | B88: nuclear-waste-services | C88: Other | D88: live | E88: nuclear-decommissioning-authority | F88: 363 | G88: 247 | H88: 22 | I88: 0 | J88: 89 | K88: 0 | L88: 0 | M88: 0 | N88: 0 | O88: 0 | P88: 1 | Q88: 14 | R88: 0 | S88: 0 | T88: 118 | U88: 3 | V88: 0 | W88: 0 | X88: No | Y88: Wave 1 — GOV.UK Content API
A89: Single Source Regulations Office | B89: single-source-regulations-office | C89: Executive non-departmental public body | D89: exempt | E89: ministry-of-defence | F89: 433 | G89: 245 | H89: 54 | I89: 18 | J89: 9 | K89: 0 | L89: 0 | M89: 1 | N89: 0 | O89: 0 | P89: 0 | Q89: 44 | R89: 20 | S89: 0 | T89: 56 | U89: 41 | V89: 0 | W89: 2 | X89: YES — off GOV.UK | Y89: Wave 2 — own-site crawl, not scoped
A90: Companies House | B90: companies-house | C90: Executive agency | D90: live | E90: department-for-business-and-trade | F90: 1420 | G90: 231 | H90: 67 | I90: 1 | J90: 56 | K90: 0 | L90: 0 | M90: 8 | N90: 1 | O90: 2 | P90: 0 | Q90: 10 | R90: 0 | S90: 2 | T90: 77 | U90: 7 | V90: 0 | W90: 0 | X90: No | Y90: Wave 1 — GOV.UK Content API
A91: Homes England | B91: homes-england | C91: Executive non-departmental public body | D91: live | E91: ministry-of-housing-communities-local-government | F91: 649 | G91: 228 | H91: 89 | I91: 0 | J91: 68 | K91: 32 | L91: 2 | M91: 5 | N91: 0 | O91: 0 | P91: 1 | Q91: 12 | R91: 0 | S91: 0 | T91: 19 | U91: 0 | V91: 0 | W91: 0 | X91: No | Y91: Wave 1 — GOV.UK Content API
A92: UK Commission for Employment and Skills | B92: uk-commission-for-employment-and-skills | C92: Executive non-departmental public body | D92: closed | E92: department-for-education | F92: 387 | G92: 227 | H92: 27 | I92: 0 | J92: 1 | K92: 0 | L92: 0 | M92: 0 | N92: 0 | O92: 0 | P92: 0 | Q92: 183 | R92: 1 | S92: 0 | T92: 13 | U92: 2 | V92: 0 | W92: 0 | X92: No | Y92: Wave 3 — archive only
A93: Highways England | B93: highways-england | C93: Other | D93: closed | E93: department-for-transport | F93: 1883 | G93: 220 | H93: 47 | I93: 0 | J93: 5 | K93: 0 | L93: 0 | M93: 5 | N93: 1 | O93: 0 | P93: 18 | Q93: 52 | R93: 0 | S93: 0 | T93: 71 | U93: 20 | V93: 1 | W93: 0 | X93: No | Y93: Wave 3 — archive only
A94: Parole Board | B94: parole-board | C94: Executive non-departmental public body | D94: live | E94: ministry-of-justice | F94: 405 | G94: 213 | H94: 81 | I94: 1 | J94: 7 | K94: 0 | L94: 0 | M94: 3 | N94: 72 | O94: 0 | P94: 0 | Q94: 1 | R94: 0 | S94: 0 | T94: 39 | U94: 0 | V94: 0 | W94: 9 | X94: No | Y94: Wave 1 — GOV.UK Content API
A95: Defence Infrastructure Organisation | B95: defence-infrastructure-organisation | C95: Sub organisation | D95: live | E95: ministry-of-defence | F95: 707 | G95: 207 | H95: 176 | I95: 0 | J95: 10 | K95: 0 | L95: 0 | M95: 2 | N95: 0 | O95: 0 | P95: 0 | Q95: 1 | R95: 3 | S95: 0 | T95: 9 | U95: 2 | V95: 1 | W95: 3 | X95: No | Y95: Wave 1 — GOV.UK Content API
A96: Office of Financial Sanctions Implementation | B96: office-of-financial-sanctions-implementation | C96: Sub organisation | D96: live | E96: hm-treasury | F96: 239 | G96: 207 | H96: 101 | I96: 35 | J96: 16 | K96: 0 | L96: 0 | M96: 4 | N96: 0 | O96: 0 | P96: 17 | Q96: 0 | R96: 0 | S96: 0 | T96: 32 | U96: 2 | V96: 0 | W96: 0 | X96: No | Y96: Wave 1 — GOV.UK Content API
A97: Conflict, Stability and Security Fund | B97: conflict-stability-and-security-fund | C97: Sub organisation | D97: closed | E97: cabinet-office | F97: 226 | G97: 202 | H97: 0 | I97: 0 | J97: 1 | K97: 0 | L97: 0 | M97: 172 | N97: 0 | O97: 0 | P97: 0 | Q97: 0 | R97: 0 | S97: 0 | T97: 29 | U97: 0 | V97: 0 | W97: 0 | X97: No | Y97: Wave 3 — archive only
A98: Defence Science and Technology Laboratory | B98: defence-science-and-technology-laboratory | C98: Executive agency | D98: live | E98: ministry-of-defence | F98: 1126 | G98: 200 | H98: 34 | I98: 0 | J98: 25 | K98: 17 | L98: 2 | M98: 1 | N98: 0 | O98: 0 | P98: 76 | Q98: 11 | R98: 2 | S98: 0 | T98: 31 | U98: 1 | V98: 0 | W98: 0 | X98: No | Y98: Wave 1 — GOV.UK Content API
A99: Legal Aid Agency | B99: legal-aid-agency | C99: Executive agency | D99: live | E99: ministry-of-justice | F99: 1303 | G99: 200 | H99: 80 | I99: 2 | J99: 59 | K99: 0 | L99: 0 | M99: 0 | N99: 1 | O99: 0 | P99: 1 | Q99: 2 | R99: 3 | S99: 0 | T99: 46 | U99: 5 | V99: 0 | W99: 1 | X99: No | Y99: Wave 1 — GOV.UK Content API
... A103: Immigration Enforcement | B103: immigration-enforcement | C103: Sub organisation | D103: live | E103: home-office | F103: 606 | G103: 190 | H103: 94 | I103: 1 | J103: 0 | K103: 0 | L103: 0 | M103: 77 | N103: 0 | O103: 0 | P103: 0 | Q103: 9 | R103: 0 | S103: 3 | T103: 2 | U103: 2 | V103: 0 | W103: 2 | X103: No | Y103: Wave 1 — GOV.UK Content API
A104: The Scottish Government | B104: the-scottish-government | C104: Devolved government | D104: exempt | F104: 753 | G104: 187 | H104: 1 | I104: 69 | J104: 7 | K104: 0 | L104: 0 | M104: 60 | N104: 0 | O104: 0 | P104: 2 | Q104: 6 | R104: 1 | S104: 0 | T104: 5 | U104: 30 | V104: 0 | W104: 6 | X104: YES — off GOV.UK | Y104: Wave 2 — own-site crawl, not scoped
A105: Office of the Secretary of State for Scotland | B105: office-of-the-secretary-of-state-for-scotland | C105: Ministerial department | D105: closed | F105: 2549 | G105: 185 | H105: 11 | I105: 0 | J105: 0 | K105: 0 | L105: 0 | M105: 56 | N105: 0 | O105: 0 | P105: 0 | Q105: 36 | R105: 2 | S105: 1 | T105: 73 | U105: 2 | V105: 3 | W105: 1 | X105: No | Y105: Wave 3 — archive only
A106: Committee on Standards in Public Life | B106: the-committee-on-standards-in-public-life | C106: Advisory non-departmental public body | D106: closed | E106: cabinet-office | F106: 604 | G106: 179 | H106: 3 | I106: 0 | J106: 0 | K106: 0 | L106: 0 | M106: 48 | N106: 0 | O106: 0 | P106: 1 | Q106: 70 | R106: 31 | S106: 1 | T106: 18 | U106: 3 | V106: 2 | W106: 2 | X106: No | Y106: Wave 3 — archive only
A107: Law Commission | B107: law-commission | C107: Advisory non-departmental public body | D107: exempt | E107: ministry-of-justice | F107: 192 | G107: 179 | H107: 0 | I107: 0 | J107: 0 | K107: 0 | L107: 0 | M107: 15 | N107: 0 | O107: 0 | P107: 0 | Q107: 113 | R107: 21 | S107: 0 | T107: 29 | U107: 1 | V107: 0 | W107: 0 | X107: YES — off GOV.UK | Y107: Wave 2 — own-site crawl, not scoped
A108: Office of Manpower Economics | B108: office-of-manpower-economics | C108: Sub organisation | D108: closed | E108: department-for-business-and-trade | F108: 340 | G108: 178 | H108: 1 | I108: 0 | J108: 0 | K108: 0 | L108: 0 | M108: 10 | N108: 0 | O108: 0 | P108: 0 | Q108: 36 | R108: 113 | S108: 0 | T108: 17 | U108: 0 | V108: 0 | W108: 1 | X108: No | Y108: Wave 3 — archive only
A109: Defence and Security Accelerator | B109: defence-and-security-accelerator | C109: Sub organisation | D109: closed | E109: ministry-of-defence | F109: 627 | G109: 176 | H109: 38 | I109: 0 | J109: 9 | K109: 0 | L109: 0 | M109: 0 | N109: 0 | O109: 0 | P109: 114 | Q109: 2 | R109: 0 | S109: 0 | T109: 13 | U109: 0 | V109: 0 | W109: 0 | X109: No | Y109: Wave 3 — archive only
A110: Veterans UK | B110: veterans-uk | C110: Sub organisation | D110: live | E110: ministry-of-defence | F110: 435 | G110: 176 | H110: 26 | I110: 0 | J110: 39 | K110: 0 | L110: 0 | M110: 4 | N110: 0 | O110: 0 | P110: 0 | Q110: 106 | R110: 0 | S110: 0 | T110: 0 | U110: 0 | V110: 0 | W110: 1 | X110: No | Y110: Wave 1 — GOV.UK Content API
A111: Building Digital UK | B111: building-digital-uk | C111: Sub organisation | D111: live | E111: department-for-science-innovation-and-technology | F111: 244 | G111: 170 | H111: 13 | I111: 0 | J111: 45 | K111: 0 | L111: 0 | M111: 17 | N111: 0 | O111: 0 | P111: 0 | Q111: 23 | R111: 0 | S111: 5 | T111: 7 | U111: 56 | V111: 0 | W111: 4 | X111: No | Y111: Wave 1 — GOV.UK Content API
A112: Student Loans Company | B112: student-loans-company | C112: Executive non-departmental public body | D112: live | E112: department-for-education | F112: 1120 | G112: 170 | H112: 53 | I112: 3 | J112: 46 | K112: 0 | L112: 0 | M112: 0 | N112: 0 | O112: 0 | P112: 0 | Q112: 0 | R112: 0 | S112: 0 | T112: 67 | U112: 1 | V112: 0 | W112: 0 | X112: No | Y112: Wave 1 — GOV.UK Content API
...

Sheet Issues Log
A1: ID | B1: Severity | C1: Affects | D1: What a user would see | E1: What is actually wrong | F1: How we fix it | G1: Decision status
A2: I01 | B2: CRITICAL | C2: Daily ingest email, all collections | D2: The email says '100% complete' next to 62 of 77 collections, so the corpus looks finished. | E2: For 46 of them the target was set by copying the number of sections we ended up with. The email prints compiled ÷ compiled, which is 100% for any corpus including an empty one. There is no upper clamp either, so explanatory-notes prints '100% complete' at 4,549% of its target. | F2: Rewrite the reporter to read a new corpus_census table, never corpus_targets.est_sections. Four states, and a percentage only where a publisher walk exists. | G2: Briefed to CC
A3: I02 | B3: CRITICAL | C3: tna-caselaw — licence | D3: Nothing visible. This is a legal exposure, not a bug. | E3: The Open Justice Licence v2.0 excludes computational analysis, which it defines to include search indexing and bulk processing. We hold 74,896 judgments, have embedded them and serve them through full-text search. | F3: Charlie writes to The National Archives for the separate computational-analysis licence. See the Licences tab, LIC01. | G3: CHARLIE — do first
A4: I03 | B4: CRITICAL | C4: fca-handbook — licence | D4: Nothing visible. | E4: FCA terms require prior written permission to reproduce or store the Handbook in any retrieval system. We are storing 3,661 sections now, and the plan is to grow that to ~150,000. | F4: Charlie writes to the FCA before any backfill. See LIC03. | G4: CHARLIE — do first
A5: I04 | B5: HIGH | C5: Case law before 2001 | D5: Ask about any leading case decided before 2001 and the platform returns nothing, or returns a modern case that cites it. It looks like the law does not exist. | E5: All four BAILII targets were retired as 'superseded by tna-caselaw'. tna-caselaw starts in 2001, so nothing superseded them. This is the largest known gap in the corpus. | F5: Walk BAILII per court per decade to size it, then fetch. Charlie writes to BAILII first. | G5: AUTHORISED 23 Aug
A6: I05 | B6: HIGH | C6: et-decisions | D6: Search an employment-law question and get back a near-empty stub page instead of the decision. | E6: 131,654 of 293,403 rows (44.9%) are a landing page, not a decision — median 18 words. They are counted as content and compete with real decisions for rank. | F6: Delete the 131,654 rows and vectors, then re-fetch the real decisions. | G6: AUTHORISED 23 Aug — delete and re-fetch
A7: I06 | B7: HIGH | C7: Three retired collections | D7: The same written question comes back twice in one result set. | E7: lda-lordswrittenquestions (20,500), lda-commonswrittenquestions (8,000) and written-statements (129) were retired, but only the target row was removed. The 28,629 sections and their vectors are still there and still served. | F7: Delete the rows AND the vectors. Prove it with a query that used to return one. | G7: AUTHORISED 23 Aug
A8: I07 | B8: HIGH | C8: tna-caselaw — content quality | D8: A case-law result whose summary is a fragment of CSS rather than the judgment. | E8: 12.7% of all embedded case-law text is stylesheet markup, and chunk 0 — the chunk most likely to be retrieved — is more than half markup in 77% of judgments. | F8: Strip the stylesheet and re-embed chunk 0. About $31 on the Gemini batch endpoint. | G8: AUTHORISED 23 Aug
A9: I08 | B9: HIGH | C9: building-regs | D9: Ask about fire safety or means of escape and get almost nothing, when Approved Document B is one of the most-read documents in the country. | E9: 21 rows at roughly 446 words each. Approved Documents run to tens of thousands of words. The PDF text is not being captured — we have the covers, not the contents. | F9: Fix PDF extraction, then re-fetch. Note that these documents incorporate BSI standards by reference, which we cannot hold — say so rather than answer as if complete. | G9: Needs a sprint
A10: I09 | B10: HIGH | C10: senedd-cofnod | D10: A Senedd result attributed to the wrong debate, or a Welsh-language passage returned to an English-language query where it cannot be read. | E10: 61.1% of 191,730 speeches carry an inherited heading from the wrong parent. Roughly 95% of a 40-row sample had Welsh-language bodies. | F10: Fix heading inheritance in the SHARED parser, not per caller. The Welsh-language question is a product decision, not an ingest one. | G10: CHARLIE DECISION on Welsh
A11: I10 | B11: HIGH | C11: written-answers | D11: A single search result containing an entire year of written answers. | E11: 143 rows at roughly 306,000 words each — whole source files stored as one section. | F11: Re-split into one section per answer. | G11: Needs a sprint
A12: I11 | B12: MEDIUM | C12: govuk-core-docs | D12: Ask for the Ministerial Code or a PACE code and get a fragment, or nothing. | E12: One 175-section collection is standing in for four separate plan rows — PACE codes, civil service and ministerial codes, Treasury Green and Magenta Books, and White Papers — estimated at 1,800+ sections combined. Nothing in it can be reported on separately. | F12: Split into four collections, then walk each. Charlie asked specifically for police and civil service codes; they are technically held but indistinguishably mixed and almost certainly incomplete. | G12: Needs a sprint
... A19: I18 | B19: LOW | C19: lgsco | D19: Ask about a council complaint and get almost nothing. | E19: 40 sections held against an internal estimate of about 100. The real published figure is likely tens of thousands. One fetch failure outstanding. | F19: Walk for a real denominator; retry the failure. | G19: Briefed to CC

Sheet Original Plan v3
A1: Corpus / Source | B1: Category | C1: Sub-category | D1: Access | E1: IP Owner | F1: Ingest Method | G1: Est. Documents | H1: Est. Sections | I1: Compilation Model | J1: Worker Phase 1 | K1: Worker Phase 2 | L1: Priority | M1: Status | N1: Notes | O1: Live corpus key(s) | P1: Sections ingested | Q1: % of Est. Sections (H) ingested | R1: Sections embedded | S1: % of Est. Sections (H) embedded | T1: % of ingested that is embedded | U1: Source-confirmed instrument coverage | V1: Coverage note (measured 2026-08-22)
A2: PRIMARY LEGISLATION
A3: UK Primary Acts (~4,500) | B3: Statute | C3: Primary | D3: Open | E3: Crown / OGL | F3: TNA CLML API | G3: 4,500 | H3: 180,000 | I3: Gemini 2.5 Flash | J3: Workers 1+2 | K3: → Hansard | L3: 1 | M3: Pending | N3: UKPGA back to 1267 (Statute of Marlborough). Split pre/post-2000 across 2 workers. | O3: primary-acts-pre-2000, primary-acts-2000plus | P3: 314078 | Q3: 174.5 | R3: 314072 | S3: 174.5 | T3: 100 | U3: ukpga 4,493 of 17,560 = 25.6% (43.7% excl. no-provisions) | V3: Source-walked: 4,493 of 17,560 published ukpga instruments present (25.6%); 99.5% for 2000+, 21.4% pre-2000.
A4: Statutory Instruments (~60,000) | B4: Statute | C4: Secondary | D4: Open | E4: Crown / OGL | F4: TNA CLML API | G4: 60,000 | H4: 600,000 | I4: Gemini 2.5 Flash | J4: Workers 3+4 | K4: → Hansard | L4: 1 | M4: Pending | N4: 3× section volume of Acts. Split pre/post-2010 across 2 workers. | O4: si-pre-2010, si-2010plus | P4: 738553 | Q4: 123.1 | R4: 738526 | S4: 123.1 | T4: 100 | U4: uksi 73,558 of 109,190 = 67.4% (72.9% excl. no-provisions) | V4: Source-walked: 73,558 of 109,190 published uksi instruments (67.4%).
A5: Retained EU Law (~4,000) | B5: Statute | C5: Secondary | D5: Open | E5: Crown / OGL | F5: TNA CLML API | G5: 4,000 | H5: 80,000 | I5: Gemini 2.5 Flash | J5: Worker 6 | K5: → BAILII phase 2 | L5: 2 | M5: Pending | N5: EU-origin instruments now on legislation.gov.uk post-Brexit. | O5: retained-eu | P5: 199224 | Q5: 249 | R5: 199224 | S5: 249 | T5: 100 | U5: eur/eudn/eudr 39,068 of 159,773 = 24.5% (84.7% excl. no-provisions) | V5: Source-walked: 39,068 of 159,773 (24.5%); 113,623 of the absences are declared no-provisions at source.
A6: Scottish Acts + SSIs | B6: Statute | C6: Devolved Primary+Secondary | D6: Open | E6: Crown / OGL | F6: TNA CLML API | H6: 90,000 | I6: Gemini 2.5 Flash | J6: Worker 5 | K6: → BAILII phase 1 | L6: 2 | M6: Pending | N6: Scottish Parliament legislation via legislation.gov.uk. | O6: regional | P6: 341093 | Q6: 379 | R6: 341083 | S6: 379 | T6: 100 | U6: asp+ssi 8,900 of 11,804 = 75.4% (90.3% excl. no-provisions) | V6: Rows 6-8 all land in the single `regional` collection; it cannot be split by nation without re-deriving from the id prefix.
A7: Welsh Acts + SIs | B7: Statute | C7: Devolved Primary+Secondary | D7: Open | E7: Crown / OGL | F7: TNA CLML API | H7: 40,000 | I7: Gemini 2.5 Flash | J7: Worker 5 | K7: → BAILII phase 1 | L7: 2 | M7: Pending | N7: Senedd legislation. | O7: regional | P7: 341093 | Q7: 852.7 | R7: 341083 | S7: 852.7 | T7: 100 | U7: wsi+anaw+asc 4,772 of 6,841 = 69.8% (97.4% excl. no-provisions) | V7: See row 6 - shared collection, not separately counted.
A8: NI Acts + Orders | B8: Statute | C8: Devolved Primary+Secondary | D8: Open | E8: Crown / OGL | F8: TNA CLML API | H8: 30,000 | I8: Gemini 2.5 Flash | J8: Worker 5 | K8: → BAILII phase 1 | L8: 2 | M8: Pending | N8: Northern Ireland Assembly + Westminster Orders in Council. | O8: regional | P8: 341093 | Q8: 1137 | R8: 341083 | S8: 1136.9 | T8: 100 | U8: nisr+nia+nisi 12,478 of 19,454 = 64.1% (95.8% excl. no-provisions) | V8: See row 6 - shared collection, not separately counted.
A9: Local / Private Acts | B9: Statute | C9: Primary | D9: Open | E9: Crown / OGL | F9: TNA CLML API | H9: 10,000 | I9: Gemini 2.5 Flash | J9: Worker 8 | K9: → Law Commission | L9: 4 | M9: Pending | N9: Lower priority – limited policy relevance. | O9: — | P9: 0 | Q9: 0 | R9: 0 | S9: 0 | T9: — | U9: — | V9: NOT INGESTED. No `ukla` seeder exists and no corpus_targets row was ever created.
A10: TAX & FINANCIAL REGULATION
A11: Tax Legislation (Finance Acts + tax SIs) | B11: Statute | C11: Tax | D11: Open | E11: Crown / OGL | F11: TNA CLML API | H11: 120,000 | I11: Gemini 2.5 Flash | J11: Workers 3+4 | K11: → Hansard | L11: 1 | M11: Pending | N11: Subset of SIs. Included in SI worker allocation. | O11: — | P11: 0 | Q11: 0 | R11: 0 | S11: 0 | T11: — | U11: — | V11: No separate collection - tax SIs sit inside si-pre-2010 / si-2010plus and are not separable here.
A12: HMRC Technical Manuals (~80 manuals) | B12: Administrative Guidance | C12: Tax | D12: Open | E12: Crown / OGL | F12: HMRC web scrape | G12: 80 | H12: 500,000 | I12: Haiku | J12: Worker 8 | K12: → Law Commission | L12: 2 | M12: ✅ Complete | N12: Already compiled. VATSAG, CTM, INTM, EIM etc. | O12: hmrc-manuals, hmrc-codes-guidance, hmrc-ancillary | P12: 83675 | Q12: 16.7 | R12: 83675 | S12: 16.7 | T12: 100 | U12: not walked - no publisher enumeration exists for this source | V12: 83,675 held against a 500,000 plan estimate.
A13: FCA Handbook (COBS, MAR, SYSC etc.) | B13: Statutory Guidance | C13: Financial Regulation | D13: Open | E13: FCA (Crown body) | F13: FCA Handbook API | H13: 150,000 | I13: Gemini 2.5 Flash | J13: Worker 7 | K13: → BAILII phase 3 | L13: 2 | M13: Pending | N13: FCA publishes structured handbook. Has a rudimentary API. | O13: fca-handbook | P13: 3661 | Q13: 2.4 | R13: 3660 | S13: 2.4 | T13: 100 | U13: not walked - no publisher enumeration exists for this source | V13: 3,661 held against a 150,000 plan estimate - the Handbook API returns far fewer units than the plan assumed.
A14: IBFD Tax Research Platform | B14: Commentary | C14: International Tax | D14: Paywalled | E14: IBFD (private) | F14: Cannot ingest | J14: — | K14: — | L14: 5 | M14: Out of scope | N14: Private IP. Cannot reproduce even with subscription. Describe existence to Lex only. | O14: — | P14: 0 | Q14: no plan estimate | R14: 0 | S14: no plan estimate | T14: — | U14: — | V14: Out of scope (private IP).
A15: REGULATORY & GUIDANCE BODIES
A16: Sentencing Council Guidelines | B16: Statutory Guidance | C16: Criminal | D16: Open | E16: Sentencing Council / Crown | F16: Web scrape (sentencingcouncil.gov.uk) | H16: 2,000 | I16: Haiku | J16: Worker 7 | K16: → BAILII phase 3 | L16: 3 | M16: Pending | O16: sentencing-council | P16: 253 | Q16: 12.7 | R16: 253 | S16: 12.7 | T16: 100 | U16: not walked - no publisher enumeration exists for this source
A17: College of Policing APP | B17: Administrative Guidance | C17: Criminal | D17: Open | E17: College of Policing | F17: Web scrape | H17: 8,000 | I17: Haiku | J17: Worker 7 | K17: → BAILII phase 3 | L17: 3 | M17: Pending | N17: Authorised Professional Practice. | O17: college-of-policing | P17: 332 | Q17: 4.2 | R17: 332 | S17: 4.2 | T17: 100 | U17: not walked - no publisher enumeration exists for this source
A18: PACE Codes A–H | B18: Statutory Guidance | C18: Criminal | D18: Open | E18: Crown / OGL | F18: gov.uk direct download | H18: 800 | I18: Haiku | J18: Worker 8 | K18: — | L18: 3 | M18: Pending | N18: Small volume; bundle with Sentencing Council worker. | O18: govuk-core-docs | P18: 175 | Q18: 21.9 | R18: 175 | S18: 21.9 | T18: 100 | U18: not walked - no publisher enumeration exists for this source | V18: Rows 18-20 and 38 share one 175-section collection (PACE + Treasury books + white papers).
A19: Civil Service / Ministerial Codes, Cabinet Manual | B19: Administrative Guidance | C19: Governance | D19: Open | E19: Crown / OGL | F19: gov.uk direct download | H19: 500 | I19: Haiku | J19: Worker 8 | K19: — | L19: 3 | M19: Pending | N19: Cabinet Manual, Ministerial Code, Civil Service Code, Better Regulation Framework. | O19: govuk-core-docs | P19: 175 | Q19: 35 | R19: 175 | S19: 35 | T19: 100 | U19: not walked - no publisher enumeration exists for this source | V19: See row 18 - shared collection.
A20: Treasury Green Book + Magenta Book | B20: Administrative Guidance | C20: Policy Methodology | D20: Open | E20: Crown / OGL | F20: gov.uk direct download | H20: 500 | I20: Haiku | J20: Worker 8 | K20: — | L20: 3 | M20: Pending | N20: Cost-benefit and evaluation frameworks. Essential for costing module. | O20: govuk-core-docs | P20: 175 | Q20: 35 | R20: 175 | S20: 35 | T20: 100 | U20: not walked - no publisher enumeration exists for this source | V20: See row 18 - shared collection.
A21: Erskine May + Parliamentary Standing Orders | B21: Administrative Guidance | C21: Parliamentary Procedure | D21: Partial | E21: Parliament | F21: parliament.uk (partial open access) | H21: 3,000 | I21: Haiku | J21: Worker 8 | K21: — | L21: 3 | M21: Pending | N21: Erskine May now free online. Standing Orders open. Full historic volumes paywalled. | O21: erskine-may | P21: 1873 | Q21: 62.4 | R21: 1873 | S21: 62.4 | T21: 100 | U21: not walked - no publisher enumeration exists for this source
A22: NHS Standard Contracts + NHSE Guidance | B22: Administrative Guidance | C22: Health | D22: Open | E22: Crown / OGL | F22: NHSE web scrape | H22: 20,000 | I22: Haiku | J22: Worker 7 | K22: → BAILII phase 3 | L22: 4 | M22: Pending | O22: — | P22: 0 | Q22: 0 | R22: 0 | S22: 0 | T22: — | U22: — | V22: NOT INGESTED. No corpus_targets row.
A23: Planning Policy (NPPF, PPG) | B23: Administrative Guidance | C23: Planning | D23: Open | E23: Crown / OGL | F23: gov.uk direct download | H23: 5,000 | I23: Haiku | J23: Worker 7 | K23: — | L23: 4 | M23: Pending | N23: National Planning Policy Framework + Planning Practice Guidance. | O23: planning-policy | P23: 64 | Q23: 1.3 | R23: 64 | S23: 1.3 | T23: 100 | U23: not walked - no publisher enumeration exists for this source | V23: 64 held against a 5,000 plan estimate.
A24: Building Regulations Approved Documents | B24: Administrative Guidance | C24: Building / Safety | D24: Open | E24: Crown / OGL | F24: gov.uk direct download | H24: 3,000 | I24: Haiku | J24: Worker 8 | K24: — | L24: 4 | M24: Pending | O24: building-regs | P24: 21 | Q24: 0.7 | R24: 21 | S24: 0.7 | T24: 100 | U24: not walked - no publisher enumeration exists for this source | V24: 21 held against a 3,000 plan estimate.
A25: CMA Guidelines + Merger Decisions | B25: Administrative Guidance | C25: Competition | D25: Open | E25: CMA / Crown | F25: CMA website scrape | H25: 8,000 | I25: Haiku | J25: Worker 8 | K25: — | L25: 4 | M25: Pending | O25: cma-cases | P25: 21525 | Q25: 269.1 | R25: 21525 | S25: 269.1 | T25: 100 | U25: not walked - no publisher enumeration exists for this source
A26: Ofcom / Ofwat / Ofgem / Ofsted Rules | B26: Statutory Guidance | C26: Regulation | D26: Open | E26: Crown bodies | F26: Individual regulator APIs / scrape | H26: 40,000 | I26: Haiku | J26: Worker 7 | K26: → BAILII phase 3 | L26: 4 | M26: Pending | N26: Each regulator has its own site; 4 separate scrapers needed. | O26: ofcom, ofgem | P26: 21312 | Q26: 53.3 | R26: 21312 | S26: 53.3 | T26: 100 | U26: not walked - no publisher enumeration exists for this source | V26: Ofwat and Ofsted were never seeded - 2 of the 4 named regulators.
A27: Other Quango Rulebooks (~466 quangos) | B27: Administrative Guidance | C27: Regulation | D27: Open | E27: Crown / OGL | F27: Web scrape (varied) | H27: 200,000 | I27: Haiku | J27: Later phase | K27: — | L27: 5 | M27: Pending | N27: Large long-tail. Automate discovery via gov.uk quango list. | O27: quangos-govuk | P27: 171030 | Q27: 85.5 | R27: 171030 | S27: 85.5 | T27: 100 | U27: not walked - no publisher enumeration exists for this source
A28: PARLIAMENTARY RECORD
A29: Hansard – Commons (1803–present) | B29: Parliamentary | C29: Debates | D29: Open | E29: Crown / Parliament / OGL | F29: Parliament API (api.parliament.uk) | G29: ~250,000 debates | H29: 2,000,000+ | I29: Haiku | J29: Workers 1+2 (Phase 2) | K29: — | L29: 2 | M29: Pending | N29: Workers 1+2 join after Acts complete. Commons debates only. | O29: pwdata-debates, historic-hansard, pwdata-westminster | P29: 11267651 | Q29: 563.4 | R29: 11267665 | S29: 563.4 | T29: 100 | U29: not walked - no publisher enumeration exists for this source | V29: Per-speech, not per-debate; the plan's unit differs from the stored unit.
A30: Hansard – Lords (1803–present) | B30: Parliamentary | C30: Debates | D30: Open | E30: Crown / Parliament / OGL | F30: Parliament API | I30: Haiku | J30: Workers 3+4 (Phase 2) | K30: — | L30: 2 | M30: Pending | N30: Workers 3+4 join after SIs complete. | O30: pwdata-lords | P30: 752805 | Q30: no plan estimate | R30: 752807 | S30: no plan estimate | T30: 100 | U30: not walked - no publisher enumeration exists for this source
A31: Bill Pages (text at each stage) | B31: Parliamentary | C31: Bills | D31: Open | E31: Crown / Parliament / OGL | F31: Parliament API + bills.parliament.uk | I31: Haiku | J31: Workers 3+4 (Phase 2) | K31: — | L31: 2 | M31: Pending | N31: Full text, explanatory notes, impact assessments at each reading. | O31: bills-api | P31: 6535 | Q31: no plan estimate | R31: 6535 | S31: no plan estimate | T31: 100 | U31: not walked - no publisher enumeration exists for this source
A32: Committee Reports (Select + Public Bill) | B32: Parliamentary | C32: Committees | D32: Open | E32: Crown / Parliament / OGL | F32: Parliament API | G32: ~15,000 reports | H32: 100,000 | I32: Haiku | J32: Workers 3+4 (Phase 2) | K32: → — | L32: 2 | M32: Pending | N32: Pre/post-legislative scrutiny. Evidence sessions. Witness lists. | O32: committees-reports, committees-evidence | P32: 464489 | Q32: 464.5 | R32: 464489 | S32: 464.5 | T32: 100 | U32: not walked - no publisher enumeration exists for this source
A33: Parliamentary Written Answers | B33: Parliamentary | C33: Written Answers | D33: Open | E33: Crown / Parliament / OGL | F33: Parliament API (api.parliament.uk) | G33: ~500,000 | H33: 300000 | I33: Haiku | J33: Workers 3+4 (Phase 2) | K33: — | L33: 2 | M33: Pending | N33: Every written answer since 2000. Minister's own interpretation of legislation at point in time. Invaluable for "what does this provision mean in practice". | O33: pwdata-wrans, pwdata-lordswrans, written-answers, lda-commonswrittenquestions, lda-lordswrittenquestions | P33: 1437234 | Q33: 479.1 | R33: 1437161 | S33: 479.1 | T33: 100 | U33: not walked - no publisher enumeration exists for this source | V33: The two lda-* collections are RETIRED as superseded but their 28,500 sections are still held and still embedded.
A34: Written Ministerial Statements | B34: Parliamentary | C34: Ministerial Statements | D34: Open | E34: Crown / Parliament / OGL | F34: Parliament API (api.parliament.uk) | G34: ~20,000 | H34: 20000 | I34: Haiku | J34: Workers 3+4 (Phase 2) | K34: — | L34: 2 | M34: Pending | N34: Formal statements made outside oral questions. Policy intent and interpretation direct from Ministers. | O34: pwdata-wms, pwdata-lordswms, written-statements | P34: 44924 | Q34: 224.6 | R34: 44924 | S34: 224.6 | T34: 100 | U34: not walked - no publisher enumeration exists for this source | V34: `written-statements` is RETIRED as superseded; its 129 sections are still held and embedded.
A35: Explanatory Notes (Acts + SIs) | B35: Explanatory | C35: Parliamentary | D35: Open | E35: Crown / OGL | F35: legislation.gov.uk API | I35: Haiku | J35: Worker 8 | K35: — | L35: 2 | M35: Pending | N35: Plain English intent statements. Available since late 1990s. | O35: explanatory-notes, explanatory-memoranda | P35: 40635 | Q35: no plan estimate | R35: 40635 | S35: no plan estimate | T35: 100 | U35: not walked - no publisher enumeration exists for this source
A36: Impact Assessments | B36: Explanatory | C36: Policy Evidence | D36: Open | E36: Crown / OGL | F36: gov.uk / legislation.gov.uk | I36: Haiku | J36: Worker 8 | K36: — | L36: 2 | M36: Pending | N36: Problem statement, counterfactuals, cost-benefit, intended outcomes. Gold for 'what were they solving'. | O36: impact-assessments | P36: 18756 | Q36: no plan estimate | R36: 18756 | S36: no plan estimate | T36: 100 | U36: not walked - no publisher enumeration exists for this source
A37: Post-Legislative Memoranda | B37: Explanatory | C37: Policy Evidence | D37: Open | E37: Crown / OGL | F37: gov.uk scrape | I37: Haiku | J37: Worker 8 | K37: — | L37: 3 | M37: Pending | N37: Patchy. 3–5 yr post-Act self-assessment. House of Commons Library tracks compliance. | O37: — | P37: 0 | Q37: no plan estimate | R37: 0 | S37: no plan estimate | T37: — | U37: — | V37: NOT INGESTED as a collection. The PIR leg is ~1,235 sections INSIDE impact-assessments.
A38: White Papers + Green Papers (Command Papers) | B38: Explanatory | C38: Policy Evidence | D38: Open | E38: Crown / OGL | F38: gov.uk + UK Parliamentary Papers | I38: Haiku | J38: Worker 8 | K38: — | L38: 3 | M38: Pending | N38: Policy intent before legislation. Royal Commission reports included. | O38: govuk-core-docs | P38: 175 | Q38: no plan estimate | R38: 175 | S38: no plan estimate | T38: 100 | U38: not walked - no publisher enumeration exists for this source | V38: See row 18 - shared collection. White/Green papers are a minority of its 175 sections.
A39: House of Commons Library Briefings | B39: Explanatory | C39: Policy Evidence | D39: Open | E39: Parliament / OGL | F39: commonslibrary.parliament.uk | I39: Haiku | J39: Worker 8 | K39: — | L39: 2 | M39: Pending | N39: Plain-English pre-Bill summaries. Exemplary research quality. Academic and stakeholder views. | O39: — | P39: 0 | Q39: no plan estimate | R39: 0 | S39: no plan estimate | T39: — | U39: — | V39: NOT INGESTED. No corpus_targets row.
A40: The Public Whip (MP voting records) | B40: Parliamentary | C40: Voting | D40: Open | E40: Public Whip (charity) | F40: publicwhip.org.uk API | I40: Haiku | J40: Later phase | K40: — | L40: 4 | M40: Pending | N40: Tracks every division vote. 'Who pushed this through / who opposed it'. | O40: — | P40: 0 | Q40: no plan estimate | R40: 0 | S40: no plan estimate | T40: — | U40: — | V40: Not in corpus_sections. Division data lives in the position graph (2.3M signals) and in lda-*/commons-divisions-votes.
A41: CASE LAW
A42: Find Case Law – TNA (2001–present) | B42: Judicial | C42: Case Law | D42: Open | E42: Crown / Open Justice Licence | F42: TNA Find Case Law API (caselaw.nationalarchives.gov.uk) | G42: ~50,000+ | I42: Haiku | J42: Worker 9 | K42: — | L42: 2 | M42: Pending | N42: Official source. Structured API. High Court, CoA, Supreme Court, Upper Tribunals. Open Justice Licence permits bulk reuse. | O42: tna-caselaw | P42: 74896 | Q42: no plan estimate | R42: 74896 | S42: no plan estimate | T42: 100 | U42: not walked - no publisher enumeration exists for this source
A43: BAILII – full corpus (pre-2003 + tribunals) | B43: Judicial | C43: Case Law | D43: Open | E43: Crown / OGL (judgments); BAILII own copyright in HTML markup only | F43: BAILII web scrape (polite, 1000ms floor) | G43: ~600,000 | H43: 2,000,000 | I43: Haiku | J43: Workers 5+6+7 (Phase 2) | K43: — | L43: 2 | M43: Pending | N43: Separate organisation from TNA – independent IP rate limit. Text of judgments: Crown copyright / OGL. BAILII's HTML markup: BAILII copyright (we compile text, not markup). Covers: EAT back to 1970s, Privy Council, Scottish courts, NI courts, tribunals, ECHR cases. | O43: — | P43: 0 | Q43: 0 | R43: 0 | S43: 0 | T43: — | U43: — | V43: NOT INGESTED. All four bailii-* corpus_targets rows are retired/blocked - superseded by tna-caselaw and et-decisions, which do not cover pre-2001.
A44: Leading Cases – curated ~10,000 | B44: Judicial | C44: Case Law | D44: Open | E44: Crown / OGL | F44: BAILII / TNA (subset) | G44: 10,000 | H44: 50,000 | I44: Gemini 2.5 Flash | J44: Worker 9 | K44: — | L44: 2 | M44: Pending | N44: Priority subset for early Lex search quality. Use Gemini for richer case summary. | O44: — | P44: 0 | Q44: 0 | R44: 0 | S44: 0 | T44: — | U44: — | V44: NOT INGESTED. No curated leading-cases subset exists.
A45: ECHR / ECtHR Judgments (HUDOC) | B45: Judicial | C45: International Case Law | D45: Open | E45: Council of Europe | F45: HUDOC API (hudoc.echr.coe.int) | I45: Haiku | J45: Worker 10 (Phase 2) | K45: — | L45: 3 | M45: Pending | N45: Separate source / separate IP / separate rate limit → own worker. UK courts must consider under HRA 1998. | O45: echr-hudoc | P45: 4410 | Q45: no plan estimate | R45: 4410 | S45: no plan estimate | T45: 100 | U45: not walked - no publisher enumeration exists for this source
A46: Law Commission Reports | B46: Judicial / Explanatory | C46: Law Reform | D46: Open | E46: Law Commission / Crown | F46: BAILII + lawcom.gov.uk | I46: Haiku | J46: Worker 8 | K46: — | L46: 2 | M46: Pending | N46: Formal analysis of why current law is broken + reform recommendations. Already on BAILII. | O46: lawcom | P46: 262 | Q46: no plan estimate | R46: 262 | S46: no plan estimate | T46: 100 | U46: not walked - no publisher enumeration exists for this source
A47: INTERNATIONAL & COMPARATIVE
A48: UK Treaties (FCO Treaties Online) | B48: International | C48: Treaties | D48: Open | E48: Crown / OGL | F48: gov.uk FCO treaty database | I48: Haiku | J48: Worker 10 (Phase 2) | K48: — | L48: 3 | M48: Pending | N48: International obligations that constrain what UK legislation can do. Back to 1892. | O48: uk-treaties-fcdo, uk-treaties, parliament-treaties, tax-treaties-dta | P48: 27274 | Q48: no plan estimate | R48: 27274 | S48: no plan estimate | T48: 100 | U48: not walked - no publisher enumeration exists for this source
A49: EU Law – EUR-Lex (retained EU law origins) | B49: International | C49: EU Law | D49: Open | E49: EU Publications Office (open) | F49: EUR-Lex API (eur-lex.europa.eu) | G49: 4,000 instruments | I49: Haiku | J49: Worker 10 (Phase 2) | K49: — | L49: 3 | M49: Pending | N49: Source directives/regulations behind retained EU law. Separate source / separate rate limit. | O49: eur-lex | P49: 241571 | Q49: no plan estimate | R49: 241571 | S49: no plan estimate | T49: 100 | U49: not walked - no publisher enumeration exists for this source
A50: OECD iLibrary – free summaries | B50: International | C50: Policy Commentary | D50: Partial | E50: OECD | F50: OECD iLibrary (free tier) | I50: Haiku | J50: Later phase | K50: — | L50: 4 | M50: Pending | N50: OECD Model Tax Convention commentary (full text paywalled). Free summaries and working papers ingestible. Full text requires negotiation / licence. | O50: oecd | P50: 505 | Q50: no plan estimate | R50: 505 | S50: no plan estimate | T50: 100 | U50: not walked - no publisher enumeration exists for this source
A51: OECD Model Tax Convention Commentary | B51: Commentary | C51: International Tax | D51: Paywalled | E51: OECD (private publication) | F51: Cannot bulk ingest | J51: — | K51: — | L51: 5 | M51: Out of scope | N51: OECD owns IP. Subscription gives read access only – no redistribution. Lex can reference existence and direct users to OECD iLibrary. | O51: — | P51: 0 | Q51: no plan estimate | R51: 0 | S51: no plan estimate | T51: — | U51: — | V51: Out of scope (OECD IP).
A52: UN / UNCITRAL | B52: International | C52: International Law | D52: Open | E52: UN (open) | F52: UNCITRAL website | I52: Haiku | J52: Later phase | K52: — | L52: 5 | M52: Pending | N52: International trade law conventions. Lower priority for UK policy platform. | O52: — | P52: 0 | Q52: no plan estimate | R52: 0 | S52: no plan estimate | T52: — | U52: — | V52: NOT INGESTED. No corpus_targets row.
A53: PUBLIC CONSULTATIONS & EVIDENCE BASE
A54: Government Public Consultations + Responses | B54: Policy Evidence | C54: Consultation | D54: Open | E54: Crown / OGL | F54: gov.uk Consultation hub API | I54: Haiku | J54: Worker 8 | K54: — | L54: 3 | M54: Pending | N54: Consultation documents + response summaries. Shows what stakeholders said before legislation passed. gov.uk has a structured consultations listing. | O54: consultations | P54: 7448 | Q54: no plan estimate | R54: 7448 | S54: no plan estimate | T54: 100 | U54: not walked - no publisher enumeration exists for this source
A55: ONS Statistical Datasets (cited in IAs) | B55: Policy Evidence | C55: Statistics | D55: Open | E55: ONS / Crown / OGL | F55: ONS API (api.ons.gov.uk) | I55: Haiku | J55: Later phase | K55: — | L55: 4 | M55: Pending | N55: Evidence base behind Impact Assessments. Metadata + headline figures rather than full datasets. | O55: — | P55: 0 | Q55: no plan estimate | R55: 0 | S55: no plan estimate | T55: — | U55: — | V55: Not in corpus_sections. ONS series live in the separate statistics store (STATS_DATABASE_URL).
A56: NAO Reports (post-implementation VFM) | B56: Policy Evidence | C56: Audit | D56: Open | E56: NAO / Crown | F56: nao.org.uk scrape | I56: Haiku | J56: Worker 8 | K56: — | L56: 3 | M56: Pending | N56: Post-implementation value-for-money assessments. 'Did it work and at what cost?' | O56: nao-reports | P56: 2570 | Q56: no plan estimate | R56: 2570 | S56: no plan estimate | T56: 100 | U56: not walked - no publisher enumeration exists for this source
A57: LEGAL SCHOLARSHIP & COMMENTARY
A58: HMRC Tax Information and Impact Notes (TIINs) | B58: Explanatory | C58: Tax Policy | D58: Open | E58: Crown / OGL | F58: gov.uk scrape | G58: ~2,500 | H58: 15000 | I58: Haiku | J58: Worker 8 | K58: — | L58: 2 | M58: Pending | N58: Published for every Finance Bill measure since 2010. Plain English explanation of policy intent behind each tax provision. Distinct from HMRC manuals. | O58: hmrc-tiins | P58: 791 | Q58: 5.3 | R58: 791 | S58: 5.3 | T58: 100 | U58: not walked - no publisher enumeration exists for this source
A59: Office of Tax Simplification Reports | B59: Commentary | C59: Tax Policy | D59: Open | E59: Crown / OGL | F59: gov.uk direct download | G59: ~50 | H59: 5000 | I59: Haiku | J59: Worker 8 | K59: — | L59: 2 | M59: Pending | N59: OTS abolished 2022 but all reports archived on gov.uk. Detailed analysis of specific tax areas (IHT, CGT, employment status). Explains what's broken and why. | O59: ots-reports | P59: 497 | Q59: 9.9 | R59: 497 | S59: 9.9 | T59: 100 | U59: not walked - no publisher enumeration exists for this source
A60: Scottish Law Commission Reports | B60: Commentary | C60: Law Reform | D60: Open | E60: Crown / OGL | F60: scotlawcom.gov.uk scrape | G60: ~200 | H60: 10000 | I60: Haiku | J60: Worker 8 | K60: — | L60: 2 | M60: Pending | N60: Scots law analysis and reform recommendations. Essential for devolved legislation. Separate from Law Commission (E&W) already in plan. | O60: scotlawcom | P60: 350 | Q60: 3.5 | R60: 350 | S60: 3.5 | T60: 100 | U60: not walked - no publisher enumeration exists for this source
A61: Northern Ireland Law Commission Reports | B61: Commentary | C61: Law Reform | D61: Open | E61: Crown / OGL | F61: nilawcommission.gov.uk scrape | G61: ~30 | H61: 2000 | I61: Haiku | J61: Worker 8 | K61: — | L61: 3 | M61: Pending | N61: NI-specific law reform analysis. Smaller volume but important for NI-specific legislation. | O61: nilawcom | P61: 17 | Q61: 0.8 | R61: 17 | S61: 0.8 | T61: 100 | U61: not walked - no publisher enumeration exists for this source
A62: SSRN UK Legal Scholarship (free tier) | B62: Commentary | C62: Academic | D62: Open | E62: Authors / Open Access | F62: SSRN API (api.ssrn.com) | G62: ~15,000 | H62: 80000 | I62: Haiku | J62: Later phase | K62: — | L62: 3 | M62: Pending | N62: Open-access legal scholarship on UK law. Papers on drafting history, policy intent, judicial interpretation. No rate limit on SSRN API. Abstracts free; full text varies. | O62: ssrn | P62: 0 | Q62: 0 | R62: 0 | S62: 0 | T62: — | U62: not walked - no publisher enumeration exists for this source | V62: BLOCKED, 0 held.
A63: COMMERCIAL / PAYWALLED – REFERENCE ONLY
A64: Halsbury's Laws of England | B64: Commentary | C64: Legal Encyclopedia | D64: Paywalled | E64: LexisNexis (Reed Elsevier) – private IP | F64: Cannot ingest | J64: — | K64: — | L64: — | M64: Out of scope | N64: Written by experts under commission. LexisNexis owns copyright in the commentary text itself (not just the platform). Subscription gives read access only. Even reproducing summaries at scale would require a licence. Lex can note 'Halsbury's covers this area' without reproducing content. Future: potential API partner / sponsorship route. | O64: — | P64: 0 | Q64: no plan estimate | R64: 0 | S64: no plan estimate | T64: — | U64: — | V64: Out of scope (private IP).
A65: Westlaw UK headnotes + Key Number System | B65: Commentary | C65: Case Annotation | D65: Paywalled | E65: Thomson Reuters – private IP | F65: Cannot ingest | J65: — | K65: — | L65: — | M65: Out of scope | N65: Thomson Reuters v ROSS (2025) confirmed headnotes are copyrightable editorial content. Underlying case text is Crown copyright / OGL and freely available via TNA. Only the annotations are paywalled. Future: potential API partner / sponsorship route — Scrutinise drives qualified traffic to their platform. | O65: — | P65: 0 | Q65: no plan estimate | R65: 0 | S65: no plan estimate | T65: — | U65: — | V65: Out of scope (private IP).
A66: LexisNexis All England Law Reports | B66: Commentary | C66: Case Reports | D66: Paywalled | E66: LexisNexis – private IP | F66: Cannot ingest | J66: — | K66: — | L66: — | M66: Out of scope | N66: Headnotes and editorial notes are LexisNexis IP. Raw judgment text is Crown copyright / free via BAILII/TNA. Future: potential API partner / sponsorship route. | O66: — | P66: 0 | Q66: no plan estimate | R66: 0 | S66: no plan estimate | T66: — | U66: — | V66: Out of scope (private IP).
A67: HeinOnline Law Journal Library | B67: Commentary | C67: Academic Journals | D67: Paywalled | E67: William S. Hein (private) | F67: Cannot ingest | J67: — | K67: — | L67: — | M67: Out of scope | N67: 3,200+ journals. Journal articles have dual copyright: journal publisher + author. Some older titles have open-access back-issues. Lex can cite article existence via CrossRef metadata. | O67: — | P67: 0 | Q67: no plan estimate | R67: 0 | S67: no plan estimate | T67: — | U67: — | V67: Out of scope (private IP).
A68: IBFD International Tax Platform | B68: Commentary | C68: International Tax | D68: Paywalled | E68: IBFD (private) | F68: Cannot ingest | J68: — | K68: — | L68: — | M68: Out of scope | N68: Private IP. No bulk access even with subscription. | O68: — | P68: 0 | Q68: no plan estimate | R68: 0 | S68: no plan estimate | T68: — | U68: — | V68: Out of scope (private IP).
A69: PREVIOUSLY UNPLANNED — HELD BUT NAMED BY NO PLAN ROW (added 2026-08-23)
A70: Scottish Parliament Official Report (1999–) | B70: Parliamentary | C70: Debates (devolved) | D70: Open | E70: Scottish Parliament / OPL | F70: parliament.scot Official Report | I70: n/a (already ingested) | L70: 3 | M70: ✅ Ingested | N70: The single largest collection the plan never named — 5.7% of everything we hold. | O70: scottish-parliament-or | P70: 1043264 | Q70: UNSIZED — no denominator | R70: 1043081 | S70: UNSIZED — no denominator | T70: 100 | U70: not walked — no publisher enumeration exists for this source | V70: The single largest collection the plan never named — 5.7% of everything we hold.
A71: Senedd Cofnod / Record of Proceedings (1999–) | B71: Parliamentary | C71: Debates (devolved) | D71: Open | E71: Senedd Commission / OGL | F71: record.senedd.wales scrape | I71: n/a (already ingested) | L71: 3 | M71: ✅ Ingested | N71: Bilingual source. See INGEST_LABELS_REPORT §4.3 — stored bodies were the WELSH rendering until 2026-08-23. | O71: senedd-cofnod | P71: 191730 | Q71: UNSIZED — no denominator | R71: 191730 | S71: UNSIZED — no denominator | T71: 100 | U71: not walked — no publisher enumeration exists for this source | V71: Bilingual source. See INGEST_LABELS_REPORT §4.3 — stored bodies were the WELSH rendering until 2026-08-23.
A72: NI Assembly Hansard (2012–) | B72: Parliamentary | C72: Debates (devolved) | D72: Open | E72: NI Assembly / OPL | F72: aims.niassembly.gov.uk | I72: n/a (already ingested) | L72: 3 | M72: ✅ Ingested | N72: Northern Ireland Assembly official report. | O72: niassembly-hansard | P72: 196348 | Q72: UNSIZED — no denominator | R72: 196348 | S72: UNSIZED — no denominator | T72: 100 | U72: not walked — no publisher enumeration exists for this source | V72: Northern Ireland Assembly official report.
A73: Employment Tribunal Decisions (2017–) | B73: Judicial | C73: Tribunal decisions | D73: Open | E73: Crown / OGL | F73: gov.uk employment-tribunal-decisions | I73: n/a (already ingested) | L73: 3 | M73: ✅ Ingested | N73: ⚠ 131,654 of 293,403 rows (44.9%) are a LANDING PAGE, not a decision — median 18 words. | O73: et-decisions | P73: 293399 | Q73: UNSIZED — no denominator | R73: 293399 | S73: UNSIZED — no denominator | T73: 100 | U73: not walked — no publisher enumeration exists for this source | V73: ⚠ 131,654 of 293,403 rows (44.9%) are a LANDING PAGE, not a decision — median 18 words.
A74: Commons Oral Questions (LDA) | B74: Parliamentary | C74: Oral Questions | D74: Open | E74: Parliament / OPL | F74: Linked Data API (data.parliament.uk) | I74: n/a (already ingested) | L74: 3 | M74: ✅ Ingested | N74: Oral questions; distinct from the pwdata per-speech debate record. | O74: lda-commonsoralquestions | P74: 69529 | Q74: UNSIZED — no denominator | R74: 69529 | S74: UNSIZED — no denominator | T74: 100 | U74: not walked — no publisher enumeration exists for this source | V74: Oral questions; distinct from the pwdata per-speech debate record.
A75: Early Day Motions | B75: Parliamentary | C75: Motions | D75: Open | E75: Parliament / OPL | F75: edm.parliament.uk | I75: n/a (already ingested) | L75: 3 | M75: ✅ Ingested | N75: Backbench opinion signal; no equivalent elsewhere in the corpus. | O75: early-day-motions | P75: 60737 | Q75: UNSIZED — no denominator | R75: 60737 | S75: UNSIZED — no denominator | T75: 100 | U75: not walked — no publisher enumeration exists for this source | V75: Backbench opinion signal; no equivalent elsewhere in the corpus.
A76: UK e-petitions (open + archived) | B76: Parliamentary | C76: Petitions | D76: Open | E76: Crown / OGL | F76: petition.parliament.uk JSON | I76: n/a (already ingested) | L76: 3 | M76: ✅ Ingested | N76: Public-initiated agenda signal with government responses. | O76: petitions | P76: 49529 | Q76: UNSIZED — no denominator | R76: 49529 | S76: UNSIZED — no denominator | T76: 100 | U76: not walked — no publisher enumeration exists for this source | V76: Public-initiated agenda signal with government responses.
A77: ICO decisions & enforcement | B77: Administrative Guidance | C77: Information Rights | D77: Open | E77: ICO / Crown | F77: ico.org.uk scrape | I77: n/a (already ingested) | L77: 3 | M77: ✅ Ingested | N77: FOI/DP decision notices and enforcement action. | O77: ico | P77: 26562 | Q77: UNSIZED — no denominator | R77: 26562 | S77: UNSIZED — no denominator | T77: 100 | U77: not walked — no publisher enumeration exists for this source | V77: FOI/DP decision notices and enforcement action.
A78: Scottish courts judgments | B78: Judicial | C78: Case Law (devolved) | D78: Open | E78: Crown / OGL | F78: scotcourts.gov.uk | I78: n/a (already ingested) | L78: 3 | M78: ✅ Ingested | N78: Not covered by TNA Find Case Law. | O78: scottish-courts | P78: 13056 | Q78: UNSIZED — no denominator | R78: 13056 | S78: UNSIZED — no denominator | T78: 100 | U78: not walked — no publisher enumeration exists for this source | V78: Not covered by TNA Find Case Law.
A79: Tax Tribunals (VAT&D / SpC / FTT-TC) | B79: Judicial | C79: Tribunal decisions | D79: Open | E79: Crown / Open Justice Licence | F79: TNA / tribunal feeds | I79: n/a (already ingested) | L79: 3 | M79: ✅ Ingested | N79: Tax-specific first-tier and special commissioner decisions. | O79: tax-tribunals | P79: 12089 | Q79: UNSIZED — no denominator | R79: 12089 | S79: UNSIZED — no denominator | T79: 100 | U79: not walked — no publisher enumeration exists for this source | V79: Tax-specific first-tier and special commissioner decisions.
A80: NI Judgments (Judiciary NI) | B80: Judicial | C80: Case Law (devolved) | D80: Open | E80: Crown / OGL | F80: judiciaryni.uk | I80: n/a (already ingested) | L80: 3 | M80: ✅ Ingested | N80: Northern Ireland courts — explicitly excluded from TNA Find Case Law. | O80: ni-judgments | P80: 7772 | Q80: UNSIZED — no denominator | R80: 7772 | S80: UNSIZED — no denominator | T80: 100 | U80: not walked — no publisher enumeration exists for this source | V80: Northern Ireland courts — explicitly excluded from TNA Find Case Law.
A81: Commons Divisions (LDA) | B81: Parliamentary | C81: Voting | D81: Open | E81: Parliament / OPL | F81: Linked Data API | I81: n/a (already ingested) | L81: 3 | M81: ✅ Ingested | N81: Division records; feeds the position graph. | O81: lda-commonsdivisions | P81: 5553 | Q81: UNSIZED — no denominator | R81: 5553 | S81: UNSIZED — no denominator | T81: 100 | U81: not walked — no publisher enumeration exists for this source | V81: Division records; feeds the position graph.
... A90: LGSCO decisions | B90: Administrative Guidance | C90: Ombudsman | D90: Open | E90: LGSCO / Crown | F90: lgo.org.uk scrape | I90: n/a (already ingested) | L90: 3 | M90: ✅ Ingested | N90: Local Government & Social Care Ombudsman decisions. | O90: lgsco | P90: 40 | Q90: UNSIZED — no denominator | R90: 40 | S90: UNSIZED — no denominator | T90: 100 | U90: not walked — no publisher enumeration exists for this source | V90: Local Government & Social Care Ombudsman decisions.

Sheet Original Legend v3
A1: Colour | B1: Meaning
A2: Blue (row) | B2: Open access – Crown copyright / OGL or equivalent free licence. Can ingest and store.
A3: Amber (row) | B3: Partial – some content free, some paywalled. Ingest free tier only.
A4: Red/Pink (row) | B4: Paywalled – private IP. Cannot reproduce even with subscription. Lex references existence only.
A5: Green (row) | B5: Already compiled and in R2.
A7: IP NOTES
A8: Crown copyright / OGL | B8: UK legislation, judgments, parliamentary material. Open Government Licence: worldwide, royalty-free, perpetual. Scrutinise can store, transform and serve this content.
A9: BAILII judgments | B9: Text of judgments = Crown copyright / OGL. BAILII's HTML markup = BAILII copyright. We compile plain text (not HTML), so we use the OGL text and avoid BAILII's own IP. Safe to ingest.
A10: TNA Find Case Law | B10: Open Justice Licence (2022). Explicitly permits copy, publish, distribute, transmit. Safe for bulk ingest.
A11: Halsbury's Laws / Westlaw headnotes / LexisNexis | B11: Private editorial IP owned by LexisNexis / Thomson Reuters. Subscription = read access only. Thomson Reuters v ROSS (2025) confirmed AI training on headnotes = infringement. Do not ingest.
A12: OECD iLibrary full text | B12: OECD publications are copyrighted by OECD. Free summaries / working papers may be ingested. Full commentary requires a content licence from OECD.
A13: EUR-Lex | B13: EU law publications: © European Union. Reuse permitted for non-commercial purposes with attribution. Scrutinise (civic tech, non-profit mission) should be fine; confirm if commercialised.
A14: ECHR / HUDOC | B14: Council of Europe. Judgments freely available. Reuse permitted with attribution.
A15: Parliament API / Hansard | B15: Parliament copyright. Open Parliament Licence (similar to OGL). Safe to ingest.

Sheet Original Reconciliation v3
A1: RECONCILIATION — does the Corpus Plan account for everything we hold?
A2: Measured 2026-08-22 01:39 UTC. Sections = corpus_sections rows with status='compiled'.
A4: Total sections held (all 80 collections) | B4: 18272435
A5: of which embedded (has a vector in corpus_vec) | B5: 18272151
A6: embedded as % of held | B6: 99.998
A7: Accounted for by a Corpus Plan row | B7: 18272435
A8: NOT accounted for by any Corpus Plan row | B8: 0
A9: as % of everything held | B9: 0
A11: COLLECTIONS HELD THAT NO PLAN ROW NAMED — all 21 given a plan row 2026-08-23 (§2)
A12: corpus key | B12: label | C12: sections held | D12: sections embedded | E12: % embedded
A13: scottish-parliament-or | B13: Scottish Parliament Official Report | C13: 1043264 | D13: 1043081 | E13: 100
A14: et-decisions | B14: Employment Tribunal Decisions (gov.uk 2017+) | C14: 293399 | D14: 293399 | E14: 100
A15: niassembly-hansard | B15: NI Assembly Hansard (2012-) | C15: 196348 | D15: 196348 | E15: 100
A16: senedd-cofnod | B16: Senedd Cofnod / Record of Proceedings (1999-) | C16: 191730 | D16: 191730 | E16: 100
A17: lda-commonsoralquestions | B17: Commons Oral Questions (LDA) | C17: 69529 | D17: 69529 | E17: 100
A18: early-day-motions | B18: Early Day Motions | C18: 60737 | D18: 60737 | E18: 100
A19: petitions | B19: UK e-petitions (open + archived) | C19: 49529 | D19: 49529 | E19: 100
A20: ico | B20: ICO decisions & enforcement | C20: 26562 | D20: 26562 | E20: 100
A21: scottish-courts | B21: Scottish courts judgments | C21: 13056 | D21: 13056 | E21: 100
A22: tax-tribunals | B22: Tax Tribunals (VAT&D/SpC/FTT-TC) | C22: 12089 | D22: 12089 | E22: 100
A23: ni-judgments | B23: NI Judgments (Judiciary NI) | C23: 7772 | D23: 7772 | E23: 100
A24: lda-commonsdivisions | B24: Commons Divisions (LDA) | C24: 5553 | D24: 5553 | E24: 100
... A33: lgsco | B33: LGSCO decisions | C33: 40 | D33: 40 | E33: 100
A35: PLAN ROWS WITH NOTHING INGESTED
A36: plan row | B36: corpus / source | C36: plan Est. Sections | D36: why
A37: 9 | B37: Local / Private Acts | C37: 10,000 | D37: NOT INGESTED. No `ukla` seeder exists and no corpus_targets row was ever created.
A38: 11 | B38: Tax Legislation (Finance Acts + tax SIs) | C38: 120,000 | D38: No separate collection - tax SIs sit inside si-pre-2010 / si-2010plus and are not separable here.
A39: 14 | B39: IBFD Tax Research Platform | D39: Out of scope (private IP).
A40: 22 | B40: NHS Standard Contracts + NHSE Guidance | C40: 20,000 | D40: NOT INGESTED. No corpus_targets row.
A41: 37 | B41: Post-Legislative Memoranda | D41: NOT INGESTED as a collection. The PIR leg is ~1,235 sections INSIDE impact-assessments.
A42: 39 | B42: House of Commons Library Briefings | D42: NOT INGESTED. No corpus_targets row.
A43: 40 | B43: The Public Whip (MP voting records) | D43: Not in corpus_sections. Division data lives in the position graph (2.3M signals) and in lda-*/commons-divisions-votes.
A44: 43 | B44: BAILII – full corpus (pre-2003 + tribunals) | C44: 2,000,000 | D44: NOT INGESTED. All four bailii-* corpus_targets rows are retired/blocked - superseded by tna-caselaw and et-decisions, which do not cover pre-2001.
A45: 44 | B45: Leading Cases – curated ~10,000 | C45: 50,000 | D45: NOT INGESTED. No curated leading-cases subset exists.
A46: 51 | B46: OECD Model Tax Convention Commentary | D46: Out of scope (OECD IP).
A47: 52 | B47: UN / UNCITRAL | D47: NOT INGESTED. No corpus_targets row.
A48: 55 | B48: ONS Statistical Datasets (cited in IAs) | D48: Not in corpus_sections. ONS series live in the separate statistics store (STATS_DATABASE_URL).
A49: 62 | B49: SSRN UK Legal Scholarship (free tier) | C49: 80000 | D49: BLOCKED, 0 held.
A50: 64 | B50: Halsbury's Laws of England | D50: Out of scope (private IP).
A51: 65 | B51: Westlaw UK headnotes + Key Number System | D51: Out of scope (private IP).
A52: 66 | B52: LexisNexis All England Law Reports | D52: Out of scope (private IP).
A53: 67 | B53: HeinOnline Law Journal Library | D53: Out of scope (private IP).
A54: 68 | B54: IBFD International Tax Platform | D54: Out of scope (private IP).
A56: §2 CLOSED 2026-08-23: 21 plan rows added, covering 1,981,946 sections.
A57: The plan now accounts for 18,272,435 of 18,272,435 held sections = 100.0% (was 89.2%).
A58: Every one of the 21 is UNSIZED by design — column H left empty. No publisher enumeration
A59: exists for any of them, and an invented denominator would be quoted as fact within a week.
